Sqrt/sqrt.v
`timescale 1ns / 1ps

//
//  逐次逼近算法求一个数的平方根
//

module sqrt#(parameter
    DATA_WIDTH  =   8
)(
    input                           clk,
    input                           rst_n,
    input                           vld_i,
    input   [DATA_WIDTH-1:0]        data_i,

    output  reg                     vld_o,
    output  reg [DATA_WIDTH/2-1:0]  data_o,
    output  reg [DATA_WIDTH/2:0]    data_r // remainder 余数
);

localparam TMP_WIDTH = DATA_WIDTH/2-1;
localparam STAGE = DATA_WIDTH/2;

reg     [DATA_WIDTH-1:0]    data_reg    [STAGE:1];  // 存储被开方数
reg     [TMP_WIDTH:0]       data_tmp1   [STAGE:1];  // 存放临时数据
reg     [TMP_WIDTH:0]       data_tmp2   [STAGE:1];
reg                         vld_tmp     [STAGE:1];

always @(posedge clk or negedge rst_n) begin
    if(!rst_n) begin
        data_reg[STAGE] <= 'd0;
        data_tmp1[STAGE] <= 'd0;
        data_tmp2[STAGE] <= 'd0;
        vld_tmp[STAGE]  <= 1'b0;
    end else if(vld_i) begin
        data_reg[STAGE] <= data_i;
        data_tmp1[STAGE] <= {1'b1,{TMP_WIDTH{1'b0}}};
        data_tmp2[STAGE] <= 'd0;
        vld_tmp[STAGE] <= 1'b1;
    end else begin
        data_reg[STAGE] <= 'd0;
        data_tmp1[STAGE] <= 'd0;
        data_tmp2[STAGE] <= 'd0;
        vld_tmp[STAGE] <= 1'b0;
    end
end

generate
    genvar i;
        for(i = TMP_WIDTH; i >= 1; i = i-1) begin : calc
            always @(posedge clk or negedge rst_n) begin
                if(!rst_n) begin
                    data_reg[i] <= 'd0;
                    data_tmp1[i] <= 'd0;
                    data_tmp2[i] <= 'd0;
                    vld_tmp[i]  <= 1'b0;
                end else if(vld_tmp[i+1]) begin
                    if(data_tmp1[i+1] * data_tmp1[i+1] > data_reg[i+1]) begin
                        data_tmp1[i] <= {data_tmp2[i+1][TMP_WIDTH:i],1'b1,{(i-1){1'b0}}};
                        data_tmp2[i] <= data_tmp2[i+1];
                    end else begin
                        data_tmp1[i] <= {data_tmp1[i+1][TMP_WIDTH:i],1'b1,{(i-1){1'b0}}};
                        data_tmp2[i] <= data_tmp1[i+1];
                    end
                    data_reg[i] <= data_reg[i+1];
                    vld_tmp[i] <= 1'b1;
                end else begin
                    data_reg[i] <= 'd0;
                    data_tmp1[i] <= 'd0;
                    data_tmp2[i] <= 'd0;
                    vld_tmp[i]  <= 1'b0;
                end
            end
        end
endgenerate

// 计算余数与最终平方根
/* verilator lint_off WIDTHTRUNC */
always @(posedge clk or negedge rst_n) begin
    if(!rst_n) begin
        vld_o <= 1'b0;
        data_o <= 'd0;
        data_r <= 'd0;
    end else if(vld_tmp[1]) begin
        vld_o <= 1'b1;
        if(data_tmp1[1]*data_tmp1[1] > data_reg[1]) begin
            data_o <= data_tmp2[1];
            data_r <= data_reg[1] - data_tmp2[1]*data_tmp2[1];
        end else begin
            data_o <= data_tmp1[1];
            data_r <= data_reg[1] - data_tmp1[1]*data_tmp1[1];
        end
    end else begin
        vld_o <= 1'b0;
        data_o <= 'd0;
        data_r <= 'd0;
    end
end

endmodule

Sqrt/waveform.vcd
$version Generated by VerilatedVcd $end
$timescale 1ps $end

 $scope module TOP $end
  $var wire  1 3 clk $end
  $var wire  8 6 data_i [7:0] $end
  $var wire  4 8 data_o [3:0] $end
  $var wire  5 9 data_r [4:0] $end
  $var wire  1 4 rst_n $end
  $var wire  1 5 vld_i $end
  $var wire  1 7 vld_o $end
  $scope module sqrt $end
   $var wire 32 : DATA_WIDTH [31:0] $end
   $var wire 32 < STAGE [31:0] $end
   $var wire 32 ; TMP_WIDTH [31:0] $end
   $var wire  1 3 clk $end
   $var wire  8 6 data_i [7:0] $end
   $var wire  4 8 data_o [3:0] $end
   $var wire  5 9 data_r [4:0] $end
   $var wire  8 # data_reg[1] [7:0] $end
   $var wire  8 $ data_reg[2] [7:0] $end
   $var wire  8 % data_reg[3] [7:0] $end
   $var wire  8 & data_reg[4] [7:0] $end
   $var wire  4 ' data_tmp1[1] [3:0] $end
   $var wire  4 ( data_tmp1[2] [3:0] $end
   $var wire  4 ) data_tmp1[3] [3:0] $end
   $var wire  4 * data_tmp1[4] [3:0] $end
   $var wire  4 + data_tmp2[1] [3:0] $end
   $var wire  4 , data_tmp2[2] [3:0] $end
   $var wire  4 - data_tmp2[3] [3:0] $end
   $var wire  4 . data_tmp2[4] [3:0] $end
   $var wire  1 4 rst_n $end
   $var wire  1 5 vld_i $end
   $var wire  1 7 vld_o $end
   $var wire  1 / vld_tmp[1] $end
   $var wire  1 0 vld_tmp[2] $end
   $var wire  1 1 vld_tmp[3] $end
   $var wire  1 2 vld_tmp[4] $end
  $upscope $end
 $upscope $end
$enddefinitions $end


#0
b00000000 #
b00000000 $
b00000000 %
b00000000 &
b0000 '
b0000 (
b0000 )
b0000 *
b0000 +
b0000 ,
b0000 -
b0000 .
0/
00
01
02
13
14
05
b00000000 6
07
b0000 8
b00000 9
b00000000000000000000000000001000 :
b00000000000000000000000000000011 ;
b00000000000000000000000000000100 <
#1
03
04
#2
13
#3
03
#4
13
#5
03
#6
13
14
#7
03
#8
13
#9
03
#10
13
#11
03
#12
13
#13
03
#14
13
#15
03
#16
13
#17
03
#18
13
15
#19
03
#20
b1000 *
12
13
05
#21
03
#22
b0100 )
b0000 *
11
02
13
#23
03
#24
b0010 (
b0000 )
10
01
13
#25
03
#26
b0001 '
b0000 (
1/
00
13
#27
03
#28
b0000 '
0/
13
15
b00000001 6
17
#29
03
#30
b00000001 &
b1000 *
12
13
05
07
#31
03
#32
b00000001 %
b00000000 &
b0100 )
b0000 *
11
02
13
#33
03
#34
b00000001 $
b00000000 %
b0010 (
b0000 )
10
01
13
#35
03
#36
b00000001 #
b00000000 $
b0001 '
b0000 (
1/
00
13
#37
03
#38
b00000000 #
b0000 '
0/
13
15
b00000010 6
17
b0001 8
#39
03
#40
b00000010 &
b1000 *
12
13
05
07
b0000 8
#41
03
#42
b00000010 %
b00000000 &
b0100 )
b0000 *
11
02
13
#43
03
#44
b00000010 $
b00000000 %
b0010 (
b0000 )
10
01
13
#45
03
#46
b00000010 #
b00000000 $
b0001 '
b0000 (
1/
00
13
#47
03
#48
b00000000 #
b0000 '
0/
13
15
b00000011 6
17
b0001 8
b00001 9
#49
03
#50
b00000011 &
b1000 *
12
13
05
07
b0000 8
b00000 9
#51
03
#52
b00000011 %
b00000000 &
b0100 )
b0000 *
11
02
13
#53
03
#54
b00000011 $
b00000000 %
b0010 (
b0000 )
10
01
13
#55
03
#56
b00000011 #
b00000000 $
b0001 '
b0000 (
1/
00
13
#57
03
#58
b00000000 #
b0000 '
0/
13
15
b00000100 6
17
b0001 8
b00010 9
#59
03
#60
b00000100 &
b1000 *
12
13
05
07
b0000 8
b00000 9
#61
03
#62
b00000100 %
b00000000 &
b0100 )
b0000 *
11
02
13
#63
03
#64
b00000100 $
b00000000 %
b0010 (
b0000 )
10
01
13
#65
03
#66
b00000100 #
b00000000 $
b0011 '
b0000 (
b0010 +
1/
00
13
#67
03
#68
b00000000 #
b0000 '
b0000 +
0/
13
15
b00000101 6
17
b0010 8
#69
03
#70
b00000101 &
b1000 *
12
13
05
07
b0000 8
#71
03
#72
b00000101 %
b00000000 &
b0100 )
b0000 *
11
02
13
#73
03
#74
b00000101 $
b00000000 %
b0010 (
b0000 )
10
01
13
#75
03
#76
b00000101 #
b00000000 $
b0011 '
b0000 (
b0010 +
1/
00
13
#77
03
#78
b00000000 #
b0000 '
b0000 +
0/
13
15
b00000110 6
17
b0010 8
b00001 9
#79
03
#80
b00000110 &
b1000 *
12
13
05
07
b0000 8
b00000 9
#81
03
#82
b00000110 %
b00000000 &
b0100 )
b0000 *
11
02
13
#83
03
#84
b00000110 $
b00000000 %
b0010 (
b0000 )
10
01
13
#85
03
#86
b00000110 #
b00000000 $
b0011 '
b0000 (
b0010 +
1/
00
13
#87
03
#88
b00000000 #
b0000 '
b0000 +
0/
13
15
b00000111 6
17
b0010 8
b00010 9
#89
03
#90
b00000111 &
b1000 *
12
13
05
07
b0000 8
b00000 9
#91
03
#92
b00000111 %
b00000000 &
b0100 )
b0000 *
11
02
13
#93
03
#94
b00000111 $
b00000000 %
b0010 (
b0000 )
10
01
13
#95
03
#96
b00000111 #
b00000000 $
b0011 '
b0000 (
b0010 +
1/
00
13
#97
03
#98
b00000000 #
b0000 '
b0000 +
0/
13
15
b00001000 6
17
b0010 8
b00011 9
#99
03
#100
b00001000 &
b1000 *
12
13
05
07
b0000 8
b00000 9
#101
03
#102
b00001000 %
b00000000 &
b0100 )
b0000 *
11
02
13
#103
03
#104
b00001000 $
b00000000 %
b0010 (
b0000 )
10
01
13
#105
03
#106
b00001000 #
b00000000 $
b0011 '
b0000 (
b0010 +
1/
00
13
#107
03
#108
b00000000 #
b0000 '
b0000 +
0/
13
15
b00001001 6
17
b0010 8
b00100 9
#109
03
#110
b00001001 &
b1000 *
12
13
05
07
b0000 8
b00000 9
#111
03
#112
b00001001 %
b00000000 &
b0100 )
b0000 *
11
02
13
#113
03
#114
b00001001 $
b00000000 %
b0010 (
b0000 )
10
01
13
#115
03
#116
b00001001 #
b00000000 $
b0011 '
b0000 (
b0010 +
1/
00
13
#117
03
#118
b00000000 #
b0000 '
b0000 +
0/
13
15
b00001010 6
17
b0011 8
#119
03
#120
b00001010 &
b1000 *
12
13
05
07
b0000 8
#121
03
#122
b00001010 %
b00000000 &
b0100 )
b0000 *
11
02
13
#123
03
#124
b00001010 $
b00000000 %
b0010 (
b0000 )
10
01
13
#125
03
#126
b00001010 #
b00000000 $
b0011 '
b0000 (
b0010 +
1/
00
13
#127
03
#128
b00000000 #
b0000 '
b0000 +
0/
13
15
b00001011 6
17
b0011 8
b00001 9
#129
03
#130
b00001011 &
b1000 *
12
13
05
07
b0000 8
b00000 9
#131
03
#132
b00001011 %
b00000000 &
b0100 )
b0000 *
11
02
13
#133
03
#134
b00001011 $
b00000000 %
b0010 (
b0000 )
10
01
13
#135
03
#136
b00001011 #
b00000000 $
b0011 '
b0000 (
b0010 +
1/
00
13
#137
03
#138
b00000000 #
b0000 '
b0000 +
0/
13
15
b00001100 6
17
b0011 8
b00010 9
#139
03
#140
b00001100 &
b1000 *
12
13
05
07
b0000 8
b00000 9
#141
03
#142
b00001100 %
b00000000 &
b0100 )
b0000 *
11
02
13
#143
03
#144
b00001100 $
b00000000 %
b0010 (
b0000 )
10
01
13
#145
03
#146
b00001100 #
b00000000 $
b0011 '
b0000 (
b0010 +
1/
00
13
#147
03
#148
b00000000 #
b0000 '
b0000 +
0/
13
15
b00001101 6
17
b0011 8
b00011 9
#149
03
#150
b00001101 &
b1000 *
12
13
05
07
b0000 8
b00000 9
#151
03
#152
b00001101 %
b00000000 &
b0100 )
b0000 *
11
02
13
#153
03
#154
b00001101 $
b00000000 %
b0010 (
b0000 )
10
01
13
#155
03
#156
b00001101 #
b00000000 $
b0011 '
b0000 (
b0010 +
1/
00
13
#157
03
#158
b00000000 #
b0000 '
b0000 +
0/
13
15
b00001110 6
17
b0011 8
b00100 9
#159
03
#160
b00001110 &
b1000 *
12
13
05
07
b0000 8
b00000 9
#161
03
#162
b00001110 %
b00000000 &
b0100 )
b0000 *
11
02
13
#163
03
#164
b00001110 $
b00000000 %
b0010 (
b0000 )
10
01
13
#165
03
#166
b00001110 #
b00000000 $
b0011 '
b0000 (
b0010 +
1/
00
13
#167
03
#168
b00000000 #
b0000 '
b0000 +
0/
13
15
b00001111 6
17
b0011 8
b00101 9
#169
03
#170
b00001111 &
b1000 *
12
13
05
07
b0000 8
b00000 9
#171
03
#172
b00001111 %
b00000000 &
b0100 )
b0000 *
11
02
13
#173
03
#174
b00001111 $
b00000000 %
b0010 (
b0000 )
10
01
13
#175
03
#176
b00001111 #
b00000000 $
b0011 '
b0000 (
b0010 +
1/
00
13
#177
03
#178
b00000000 #
b0000 '
b0000 +
0/
13
15
b00010000 6
17
b0011 8
b00110 9
#179
03
#180
b00010000 &
b1000 *
12
13
05
07
b0000 8
b00000 9
#181
03
#182
b00010000 %
b00000000 &
b0100 )
b0000 *
11
02
13
#183
03
#184
b00010000 $
b00000000 %
b0110 (
b0000 )
b0100 ,
10
01
13
#185
03
#186
b00010000 #
b00000000 $
b0101 '
b0000 (
b0100 +
b0000 ,
1/
00
13
#187
03
#188
b00000000 #
b0000 '
b0000 +
0/
13
15
b00010001 6
17
b0100 8
#189
03
#190
b00010001 &
b1000 *
12
13
05
07
b0000 8
#191
03
#192
b00010001 %
b00000000 &
b0100 )
b0000 *
11
02
13
#193
03
#194
b00010001 $
b00000000 %
b0110 (
b0000 )
b0100 ,
10
01
13
#195
03
#196
b00010001 #
b00000000 $
b0101 '
b0000 (
b0100 +
b0000 ,
1/
00
13
#197
03
#198
b00000000 #
b0000 '
b0000 +
0/
13
15
b00010010 6
17
b0100 8
b00001 9
#199
03
#200
b00010010 &
b1000 *
12
13
05
07
b0000 8
b00000 9
#201
03
#202
b00010010 %
b00000000 &
b0100 )
b0000 *
11
02
13
#203
03
#204
b00010010 $
b00000000 %
b0110 (
b0000 )
b0100 ,
10
01
13
#205
03
#206
b00010010 #
b00000000 $
b0101 '
b0000 (
b0100 +
b0000 ,
1/
00
13
#207
03
#208
b00000000 #
b0000 '
b0000 +
0/
13
15
b00010011 6
17
b0100 8
b00010 9
#209
03
#210
b00010011 &
b1000 *
12
13
05
07
b0000 8
b00000 9
#211
03
#212
b00010011 %
b00000000 &
b0100 )
b0000 *
11
02
13
#213
03
#214
b00010011 $
b00000000 %
b0110 (
b0000 )
b0100 ,
10
01
13
#215
03
#216
b00010011 #
b00000000 $
b0101 '
b0000 (
b0100 +
b0000 ,
1/
00
13
#217
03
#218
b00000000 #
b0000 '
b0000 +
0/
13
15
b00010100 6
17
b0100 8
b00011 9
#219
03
#220
b00010100 &
b1000 *
12
13
05
07
b0000 8
b00000 9
#221
03
#222
b00010100 %
b00000000 &
b0100 )
b0000 *
11
02
13
#223
03
#224
b00010100 $
b00000000 %
b0110 (
b0000 )
b0100 ,
10
01
13
#225
03
#226
b00010100 #
b00000000 $
b0101 '
b0000 (
b0100 +
b0000 ,
1/
00
13
#227
03
#228
b00000000 #
b0000 '
b0000 +
0/
13
15
b00010101 6
17
b0100 8
b00100 9
#229
03
#230
b00010101 &
b1000 *
12
13
05
07
b0000 8
b00000 9
#231
03
#232
b00010101 %
b00000000 &
b0100 )
b0000 *
11
02
13
#233
03
#234
b00010101 $
b00000000 %
b0110 (
b0000 )
b0100 ,
10
01
13
#235
03
#236
b00010101 #
b00000000 $
b0101 '
b0000 (
b0100 +
b0000 ,
1/
00
13
#237
03
#238
b00000000 #
b0000 '
b0000 +
0/
13
15
b00010110 6
17
b0100 8
b00101 9
#239
03
#240
b00010110 &
b1000 *
12
13
05
07
b0000 8
b00000 9
#241
03
#242
b00010110 %
b00000000 &
b0100 )
b0000 *
11
02
13
#243
03
#244
b00010110 $
b00000000 %
b0110 (
b0000 )
b0100 ,
10
01
13
#245
03
#246
b00010110 #
b00000000 $
b0101 '
b0000 (
b0100 +
b0000 ,
1/
00
13
#247
03
#248
b00000000 #
b0000 '
b0000 +
0/
13
15
b00010111 6
17
b0100 8
b00110 9
#249
03
#250
b00010111 &
b1000 *
12
13
05
07
b0000 8
b00000 9
#251
03
#252
b00010111 %
b00000000 &
b0100 )
b0000 *
11
02
13
#253
03
#254
b00010111 $
b00000000 %
b0110 (
b0000 )
b0100 ,
10
01
13
#255
03
#256
b00010111 #
b00000000 $
b0101 '
b0000 (
b0100 +
b0000 ,
1/
00
13
#257
03
#258
b00000000 #
b0000 '
b0000 +
0/
13
15
b00011000 6
17
b0100 8
b00111 9
#259
03
#260
b00011000 &
b1000 *
12
13
05
07
b0000 8
b00000 9
#261
03
#262
b00011000 %
b00000000 &
b0100 )
b0000 *
11
02
13
#263
03
#264
b00011000 $
b00000000 %
b0110 (
b0000 )
b0100 ,
10
01
13
#265
03
#266
b00011000 #
b00000000 $
b0101 '
b0000 (
b0100 +
b0000 ,
1/
00
13
#267
03
#268
b00000000 #
b0000 '
b0000 +
0/
13
15
b00011001 6
17
b0100 8
b01000 9
#269
03
#270
b00011001 &
b1000 *
12
13
05
07
b0000 8
b00000 9
#271
03
#272
b00011001 %
b00000000 &
b0100 )
b0000 *
11
02
13
#273
03
#274
b00011001 $
b00000000 %
b0110 (
b0000 )
b0100 ,
10
01
13
#275
03
#276
b00011001 #
b00000000 $
b0101 '
b0000 (
b0100 +
b0000 ,
1/
00
13
#277
03
#278
b00000000 #
b0000 '
b0000 +
0/
13
15
b00011010 6
17
b0101 8
#279
03
#280
b00011010 &
b1000 *
12
13
05
07
b0000 8
#281
03
#282
b00011010 %
b00000000 &
b0100 )
b0000 *
11
02
13
#283
03
#284
b00011010 $
b00000000 %
b0110 (
b0000 )
b0100 ,
10
01
13
#285
03
#286
b00011010 #
b00000000 $
b0101 '
b0000 (
b0100 +
b0000 ,
1/
00
13
#287
03
#288
b00000000 #
b0000 '
b0000 +
0/
13
15
b00011011 6
17
b0101 8
b00001 9
#289
03
#290
b00011011 &
b1000 *
12
13
05
07
b0000 8
b00000 9
#291
03
#292
b00011011 %
b00000000 &
b0100 )
b0000 *
11
02
13
#293
03
#294
b00011011 $
b00000000 %
b0110 (
b0000 )
b0100 ,
10
01
13
#295
03
#296
b00011011 #
b00000000 $
b0101 '
b0000 (
b0100 +
b0000 ,
1/
00
13
#297
03
#298
b00000000 #
b0000 '
b0000 +
0/
13
15
b00011100 6
17
b0101 8
b00010 9
#299
03
#300
b00011100 &
b1000 *
12
13
05
07
b0000 8
b00000 9
#301
03
#302
b00011100 %
b00000000 &
b0100 )
b0000 *
11
02
13
#303
03
#304
b00011100 $
b00000000 %
b0110 (
b0000 )
b0100 ,
10
01
13
#305
03
#306
b00011100 #
b00000000 $
b0101 '
b0000 (
b0100 +
b0000 ,
1/
00
13
#307
03
#308
b00000000 #
b0000 '
b0000 +
0/
13
15
b00011101 6
17
b0101 8
b00011 9
#309
03
#310
b00011101 &
b1000 *
12
13
05
07
b0000 8
b00000 9
#311
03
#312
b00011101 %
b00000000 &
b0100 )
b0000 *
11
02
13
#313
03
#314
b00011101 $
b00000000 %
b0110 (
b0000 )
b0100 ,
10
01
13
#315
03
#316
b00011101 #
b00000000 $
b0101 '
b0000 (
b0100 +
b0000 ,
1/
00
13
#317
03
#318
b00000000 #
b0000 '
b0000 +
0/
13
15
b00011110 6
17
b0101 8
b00100 9
#319
03
#320
b00011110 &
b1000 *
12
13
05
07
b0000 8
b00000 9
#321
03
#322
b00011110 %
b00000000 &
b0100 )
b0000 *
11
02
13
#323
03
#324
b00011110 $
b00000000 %
b0110 (
b0000 )
b0100 ,
10
01
13
#325
03
#326
b00011110 #
b00000000 $
b0101 '
b0000 (
b0100 +
b0000 ,
1/
00
13
#327
03
#328
b00000000 #
b0000 '
b0000 +
0/
13
15
b00011111 6
17
b0101 8
b00101 9
#329
03
#330
b00011111 &
b1000 *
12
13
05
07
b0000 8
b00000 9
#331
03
#332
b00011111 %
b00000000 &
b0100 )
b0000 *
11
02
13
#333
03
#334
b00011111 $
b00000000 %
b0110 (
b0000 )
b0100 ,
10
01
13
#335
03
#336
b00011111 #
b00000000 $
b0101 '
b0000 (
b0100 +
b0000 ,
1/
00
13
#337
03
#338
b00000000 #
b0000 '
b0000 +
0/
13
15
b00100000 6
17
b0101 8
b00110 9
#339
03
#340
b00100000 &
b1000 *
12
13
05
07
b0000 8
b00000 9
#341
03
#342
b00100000 %
b00000000 &
b0100 )
b0000 *
11
02
13
#343
03
#344
b00100000 $
b00000000 %
b0110 (
b0000 )
b0100 ,
10
01
13
#345
03
#346
b00100000 #
b00000000 $
b0101 '
b0000 (
b0100 +
b0000 ,
1/
00
13
#347
03
#348
b00000000 #
b0000 '
b0000 +
0/
13
15
b00100001 6
17
b0101 8
b00111 9
#349
03
#350
b00100001 &
b1000 *
12
13
05
07
b0000 8
b00000 9
#351
03
#352
b00100001 %
b00000000 &
b0100 )
b0000 *
11
02
13
#353
03
#354
b00100001 $
b00000000 %
b0110 (
b0000 )
b0100 ,
10
01
13
#355
03
#356
b00100001 #
b00000000 $
b0101 '
b0000 (
b0100 +
b0000 ,
1/
00
13
#357
03
#358
b00000000 #
b0000 '
b0000 +
0/
13
15
b00100010 6
17
b0101 8
b01000 9
#359
03
#360
b00100010 &
b1000 *
12
13
05
07
b0000 8
b00000 9
#361
03
#362
b00100010 %
b00000000 &
b0100 )
b0000 *
11
02
13
#363
03
#364
b00100010 $
b00000000 %
b0110 (
b0000 )
b0100 ,
10
01
13
#365
03
#366
b00100010 #
b00000000 $
b0101 '
b0000 (
b0100 +
b0000 ,
1/
00
13
#367
03
#368
b00000000 #
b0000 '
b0000 +
0/
13
15
b00100011 6
17
b0101 8
b01001 9
#369
03
#370
b00100011 &
b1000 *
12
13
05
07
b0000 8
b00000 9
#371
03
#372
b00100011 %
b00000000 &
b0100 )
b0000 *
11
02
13
#373
03
#374
b00100011 $
b00000000 %
b0110 (
b0000 )
b0100 ,
10
01
13
#375
03
#376
b00100011 #
b00000000 $
b0101 '
b0000 (
b0100 +
b0000 ,
1/
00
13
#377
03
#378
b00000000 #
b0000 '
b0000 +
0/
13
15
b00100100 6
17
b0101 8
b01010 9
#379
03
#380
b00100100 &
b1000 *
12
13
05
07
b0000 8
b00000 9
#381
03
#382
b00100100 %
b00000000 &
b0100 )
b0000 *
11
02
13
#383
03
#384
b00100100 $
b00000000 %
b0110 (
b0000 )
b0100 ,
10
01
13
#385
03
#386
b00100100 #
b00000000 $
b0111 '
b0000 (
b0110 +
b0000 ,
1/
00
13
#387
03
#388
b00000000 #
b0000 '
b0000 +
0/
13
15
b00100101 6
17
b0110 8
#389
03
#390
b00100101 &
b1000 *
12
13
05
07
b0000 8
#391
03
#392
b00100101 %
b00000000 &
b0100 )
b0000 *
11
02
13
#393
03
#394
b00100101 $
b00000000 %
b0110 (
b0000 )
b0100 ,
10
01
13
#395
03
#396
b00100101 #
b00000000 $
b0111 '
b0000 (
b0110 +
b0000 ,
1/
00
13
#397
03
#398
b00000000 #
b0000 '
b0000 +
0/
13
15
b00100110 6
17
b0110 8
b00001 9
#399
03
#400
b00100110 &
b1000 *
12
13
05
07
b0000 8
b00000 9
#401
03
#402
b00100110 %
b00000000 &
b0100 )
b0000 *
11
02
13
#403
03
#404
b00100110 $
b00000000 %
b0110 (
b0000 )
b0100 ,
10
01
13
#405
03
#406
b00100110 #
b00000000 $
b0111 '
b0000 (
b0110 +
b0000 ,
1/
00
13
#407
03
#408
b00000000 #
b0000 '
b0000 +
0/
13
15
b00100111 6
17
b0110 8
b00010 9
#409
03
#410
b00100111 &
b1000 *
12
13
05
07
b0000 8
b00000 9
#411
03
#412
b00100111 %
b00000000 &
b0100 )
b0000 *
11
02
13
#413
03
#414
b00100111 $
b00000000 %
b0110 (
b0000 )
b0100 ,
10
01
13
#415
03
#416
b00100111 #
b00000000 $
b0111 '
b0000 (
b0110 +
b0000 ,
1/
00
13
#417
03
#418
b00000000 #
b0000 '
b0000 +
0/
13
15
b00101000 6
17
b0110 8
b00011 9
#419
03
#420
b00101000 &
b1000 *
12
13
05
07
b0000 8
b00000 9
#421
03
#422
b00101000 %
b00000000 &
b0100 )
b0000 *
11
02
13
#423
03
#424
b00101000 $
b00000000 %
b0110 (
b0000 )
b0100 ,
10
01
13
#425
03
#426
b00101000 #
b00000000 $
b0111 '
b0000 (
b0110 +
b0000 ,
1/
00
13
#427
03
#428
b00000000 #
b0000 '
b0000 +
0/
13
15
b00101001 6
17
b0110 8
b00100 9
#429
03
#430
b00101001 &
b1000 *
12
13
05
07
b0000 8
b00000 9
#431
03
#432
b00101001 %
b00000000 &
b0100 )
b0000 *
11
02
13
#433
03
#434
b00101001 $
b00000000 %
b0110 (
b0000 )
b0100 ,
10
01
13
#435
03
#436
b00101001 #
b00000000 $
b0111 '
b0000 (
b0110 +
b0000 ,
1/
00
13
#437
03
#438
b00000000 #
b0000 '
b0000 +
0/
13
15
b00101010 6
17
b0110 8
b00101 9
#439
03
#440
b00101010 &
b1000 *
12
13
05
07
b0000 8
b00000 9
#441
03
#442
b00101010 %
b00000000 &
b0100 )
b0000 *
11
02
13
#443
03
#444
b00101010 $
b00000000 %
b0110 (
b0000 )
b0100 ,
10
01
13
#445
03
#446
b00101010 #
b00000000 $
b0111 '
b0000 (
b0110 +
b0000 ,
1/
00
13
#447
03
#448
b00000000 #
b0000 '
b0000 +
0/
13
15
b00101011 6
17
b0110 8
b00110 9
#449
03
#450
b00101011 &
b1000 *
12
13
05
07
b0000 8
b00000 9
#451
03
#452
b00101011 %
b00000000 &
b0100 )
b0000 *
11
02
13
#453
03
#454
b00101011 $
b00000000 %
b0110 (
b0000 )
b0100 ,
10
01
13
#455
03
#456
b00101011 #
b00000000 $
b0111 '
b0000 (
b0110 +
b0000 ,
1/
00
13
#457
03
#458
b00000000 #
b0000 '
b0000 +
0/
13
15
b00101100 6
17
b0110 8
b00111 9
#459
03
#460
b00101100 &
b1000 *
12
13
05
07
b0000 8
b00000 9
#461
03
#462
b00101100 %
b00000000 &
b0100 )
b0000 *
11
02
13
#463
03
#464
b00101100 $
b00000000 %
b0110 (
b0000 )
b0100 ,
10
01
13
#465
03
#466
b00101100 #
b00000000 $
b0111 '
b0000 (
b0110 +
b0000 ,
1/
00
13
#467
03
#468
b00000000 #
b0000 '
b0000 +
0/
13
15
b00101101 6
17
b0110 8
b01000 9
#469
03
#470
b00101101 &
b1000 *
12
13
05
07
b0000 8
b00000 9
#471
03
#472
b00101101 %
b00000000 &
b0100 )
b0000 *
11
02
13
#473
03
#474
b00101101 $
b00000000 %
b0110 (
b0000 )
b0100 ,
10
01
13
#475
03
#476
b00101101 #
b00000000 $
b0111 '
b0000 (
b0110 +
b0000 ,
1/
00
13
#477
03
#478
b00000000 #
b0000 '
b0000 +
0/
13
15
b00101110 6
17
b0110 8
b01001 9
#479
03
#480
b00101110 &
b1000 *
12
13
05
07
b0000 8
b00000 9
#481
03
#482
b00101110 %
b00000000 &
b0100 )
b0000 *
11
02
13
#483
03
#484
b00101110 $
b00000000 %
b0110 (
b0000 )
b0100 ,
10
01
13
#485
03
#486
b00101110 #
b00000000 $
b0111 '
b0000 (
b0110 +
b0000 ,
1/
00
13
#487
03
#488
b00000000 #
b0000 '
b0000 +
0/
13
15
b00101111 6
17
b0110 8
b01010 9
#489
03
#490
b00101111 &
b1000 *
12
13
05
07
b0000 8
b00000 9
#491
03
#492
b00101111 %
b00000000 &
b0100 )
b0000 *
11
02
13
#493
03
#494
b00101111 $
b00000000 %
b0110 (
b0000 )
b0100 ,
10
01
13
#495
03
#496
b00101111 #
b00000000 $
b0111 '
b0000 (
b0110 +
b0000 ,
1/
00
13
#497
03
#498
b00000000 #
b0000 '
b0000 +
0/
13
15
b00110000 6
17
b0110 8
b01011 9
#499
03
#500
b00110000 &
b1000 *
12
13
05
07
b0000 8
b00000 9
#501
03
#502
b00110000 %
b00000000 &
b0100 )
b0000 *
11
02
13
#503
03
#504
b00110000 $
b00000000 %
b0110 (
b0000 )
b0100 ,
10
01
13
#505
03
#506
b00110000 #
b00000000 $
b0111 '
b0000 (
b0110 +
b0000 ,
1/
00
13
#507
03
#508
b00000000 #
b0000 '
b0000 +
0/
13
15
b00110001 6
17
b0110 8
b01100 9
#509
03
#510
b00110001 &
b1000 *
12
13
05
07
b0000 8
b00000 9
#511
03
#512
b00110001 %
b00000000 &
b0100 )
b0000 *
11
02
13
#513
03
#514
b00110001 $
b00000000 %
b0110 (
b0000 )
b0100 ,
10
01
13
#515
03
#516
b00110001 #
b00000000 $
b0111 '
b0000 (
b0110 +
b0000 ,
1/
00
13
#517
03
#518
b00000000 #
b0000 '
b0000 +
0/
13
15
b00110010 6
17
b0111 8
#519
03
#520
b00110010 &
b1000 *
12
13
05
07
b0000 8
#521
03
#522
b00110010 %
b00000000 &
b0100 )
b0000 *
11
02
13
#523
03
#524
b00110010 $
b00000000 %
b0110 (
b0000 )
b0100 ,
10
01
13
#525
03
#526
b00110010 #
b00000000 $
b0111 '
b0000 (
b0110 +
b0000 ,
1/
00
13
#527
03
#528
b00000000 #
b0000 '
b0000 +
0/
13
15
b00110011 6
17
b0111 8
b00001 9
#529
03
#530
b00110011 &
b1000 *
12
13
05
07
b0000 8
b00000 9
#531
03
#532
b00110011 %
b00000000 &
b0100 )
b0000 *
11
02
13
#533
03
#534
b00110011 $
b00000000 %
b0110 (
b0000 )
b0100 ,
10
01
13
#535
03
#536
b00110011 #
b00000000 $
b0111 '
b0000 (
b0110 +
b0000 ,
1/
00
13
#537
03
#538
b00000000 #
b0000 '
b0000 +
0/
13
15
b00110100 6
17
b0111 8
b00010 9
#539
03
#540
b00110100 &
b1000 *
12
13
05
07
b0000 8
b00000 9
#541
03
#542
b00110100 %
b00000000 &
b0100 )
b0000 *
11
02
13
#543
03
#544
b00110100 $
b00000000 %
b0110 (
b0000 )
b0100 ,
10
01
13
#545
03
#546
b00110100 #
b00000000 $
b0111 '
b0000 (
b0110 +
b0000 ,
1/
00
13
#547
03
#548
b00000000 #
b0000 '
b0000 +
0/
13
15
b00110101 6
17
b0111 8
b00011 9
#549
03
#550
b00110101 &
b1000 *
12
13
05
07
b0000 8
b00000 9
#551
03
#552
b00110101 %
b00000000 &
b0100 )
b0000 *
11
02
13
#553
03
#554
b00110101 $
b00000000 %
b0110 (
b0000 )
b0100 ,
10
01
13
#555
03
#556
b00110101 #
b00000000 $
b0111 '
b0000 (
b0110 +
b0000 ,
1/
00
13
#557
03
#558
b00000000 #
b0000 '
b0000 +
0/
13
15
b00110110 6
17
b0111 8
b00100 9
