ReqAck/reqack.v
module reqack #(parameter
    DATA_WIDTH  =   8
)(
    input                           clka,
    input                           rst_n,
    input   reg                     req,
    input   [DATA_WIDTH-1:0]        data_a,
    output  reg                     ack_s,

    input                           clkb,
    output  reg                     ack,
    output  reg [DATA_WIDTH-1:0]    data_b
);

reg     req_toggle_s;
always @(posedge clka or negedge rst_n) begin
    if(!rst_n)
        req_toggle_s <= 1'b0;
    else if(req)
        req_toggle_s <= ~req_toggle_s;
    else
        req_toggle_s <= req_toggle_s;
end

reg     req_toggle_sync1;
reg     req_toggle_sync2;
always @(posedge clkb or negedge rst_n) begin
    if(!rst_n) begin
        req_toggle_sync1 <= 1'b0;
        req_toggle_sync2 <= 1'b0;
    end else begin
        req_toggle_sync1 <= req_toggle_s;
        req_toggle_sync2 <= req_toggle_sync1;
    end
end

wire    req_sync;
assign req_sync = req_toggle_sync1 ^ req_toggle_sync2;

always @(posedge clkb or negedge rst_n) begin
    if(!rst_n) begin
        ack <= 1'b0;
        data_b <= 'd0;
    end
    else if(req_sync) begin
        ack <= req_sync;
        data_b <= data_a;
    end else begin
        ack <= 1'b0;
        data_b <= 'd0;
    end
end

reg     ack_toggle_s;
always @(posedge clkb or negedge rst_n) begin
    if(!rst_n)
        ack_toggle_s <= 1'b0;
    else if(ack)
        ack_toggle_s <= ~ack_toggle_s;
    else
        ack_toggle_s <= ack_toggle_s;
end

reg     ack_toggle_sync1;
reg     ack_toggle_sync2;
always @(posedge clka or negedge rst_n) begin
    if(!rst_n) begin
        ack_toggle_sync1 <= 1'b0;
        ack_toggle_sync2 <= 1'b0;
    end else begin
        ack_toggle_sync1 <= ack_toggle_s;
        ack_toggle_sync2 <= ack_toggle_sync1;
    end
end

wire    ack_sync;
assign ack_sync = ack_toggle_sync1 ^ ack_toggle_sync2;

always @(posedge clka or negedge rst_n) begin
    if(!rst_n)
        ack_s <= 1'b0;
    else
        ack_s <= ack_sync;
end

endmodule

ReqAck/waveform.vcd
$version Generated by VerilatedVcd $end
$timescale 1ps $end

 $scope module TOP $end
  $var wire  1 0 ack $end
  $var wire  1 . ack_s $end
  $var wire  1 * clka $end
  $var wire  1 / clkb $end
  $var wire  8 - data_a [7:0] $end
  $var wire  8 1 data_b [7:0] $end
  $var wire  1 , req $end
  $var wire  1 + rst_n $end
  $scope module reqack $end
   $var wire 32 3 DATA_WIDTH [31:0] $end
   $var wire  1 0 ack $end
   $var wire  1 . ack_s $end
   $var wire  1 % ack_sync $end
   $var wire  1 ) ack_toggle_s $end
   $var wire  1 # ack_toggle_sync1 $end
   $var wire  1 $ ack_toggle_sync2 $end
   $var wire  1 * clka $end
   $var wire  1 / clkb $end
   $var wire  8 - data_a [7:0] $end
   $var wire  8 1 data_b [7:0] $end
   $var wire  1 , req $end
   $var wire  1 ( req_sync $end
   $var wire  1 2 req_toggle_s $end
   $var wire  1 & req_toggle_sync1 $end
   $var wire  1 ' req_toggle_sync2 $end
   $var wire  1 + rst_n $end
  $upscope $end
 $upscope $end
$enddefinitions $end


#0
0#
0$
0%
0&
0'
0(
0)
1*
1+
0,
b00000000 -
0.
1/
00
b00000000 1
02
b00000000000000000000000000001000 3
#1
0*
0+
#2
1*
0/
#3
0*
#4
1*
1/
#5
0*
#6
1*
1+
0/
#7
0*
#8
1*
1/
#9
0*
#10
1*
0/
#11
0*
#12
1*
1/
#13
0*
#14
1*
0/
#15
0*
#16
1*
1/
#17
0*
#18
1*
0/
#19
0*
#20
1*
1/
#21
0*
#22
1*
0/
#23
0*
#24
1*
1/
#25
0*
#26
1*
0/
#27
0*
#28
1*
1/
#29
0*
#30
1*
0/
#31
0*
#32
1*
1/
#33
0*
#34
1*
0/
#35
0*
#36
1*
1/
#37
0*
#38
1*
1,
b00010111 -
0/
#39
0*
#40
1*
0,
1/
12
#41
0*
#42
1*
0/
#43
0*
#44
1&
1(
1*
1/
#45
0*
#46
1*
0/
#47
0*
#48
1'
0(
1*
1/
10
b00010111 1
#49
0*
#50
1*
0/
#51
0*
#52
1)
1*
1/
00
b00000000 1
#53
0*
#54
1#
1%
1*
0/
#55
0*
#56
1$
0%
1*
1,
b00100000 -
1.
1/
#57
0*
#58
1*
0,
0.
0/
02
#59
0*
#60
0&
1(
1*
1/
#61
0*
#62
1*
0/
#63
0*
#64
0'
0(
1*
1/
10
b00100000 1
#65
0*
#66
1*
0/
#67
0*
#68
0)
1*
1/
00
b00000000 1
#69
0*
#70
0#
1%
1*
0/
#71
0*
#72
0$
0%
1*
1,
1.
1/
#73
0*
#74
1*
0,
0.
0/
12
#75
0*
#76
1&
1(
1*
1/
#77
0*
#78
1*
0/
#79
0*
#80
1'
0(
1*
1/
10
b00100000 1
#81
0*
#82
1*
0/
#83
0*
#84
1)
1*
1/
00
b00000000 1
#85
0*
#86
1#
1%
1*
0/
#87
0*
#88
1$
0%
1*
1,
1.
1/
#89
0*
#90
1*
0,
0.
0/
02
#91
0*
#92
0&
1(
1*
1/
#93
0*
#94
1*
0/
#95
0*
#96
0'
0(
1*
1/
10
b00100000 1
#97
0*
#98
1*
0/
#99
0*
#100
0)
1*
1/
00
b00000000 1
#101
0*
#102
0#
1%
1*
0/
#103
0*
#104
0$
0%
1*
1,
1.
1/
#105
0*
#106
1*
0,
0.
0/
12
#107
0*
#108
1&
1(
1*
1/
#109
0*
#110
1*
0/
#111
0*
#112
1'
0(
1*
1/
10
b00100000 1
#113
0*
#114
1*
0/
#115
0*
#116
1)
1*
1/
00
b00000000 1
#117
0*
#118
1#
1%
1*
0/
#119
0*
#120
1$
0%
1*
1,
1.
1/
#121
0*
#122
1*
0,
0.
0/
02
#123
0*
#124
0&
1(
1*
1/
#125
0*
#126
1*
0/
#127
0*
#128
0'
0(
1*
1/
10
b00100000 1
#129
0*
#130
1*
0/
#131
0*
#132
0)
1*
1/
00
b00000000 1
#133
0*
#134
0#
1%
1*
0/
#135
0*
#136
0$
0%
1*
1,
1.
1/
#137
0*
#138
1*
0,
0.
0/
12
#139
0*
#140
1&
1(
1*
1/
#141
0*
#142
1*
0/
#143
0*
#144
1'
0(
1*
1/
10
b00100000 1
#145
0*
#146
1*
0/
#147
0*
#148
1)
1*
1/
00
b00000000 1
#149
0*
#150
1#
1%
1*
0/
#151
0*
#152
1$
0%
1*
1,
1.
1/
#153
0*
#154
1*
0,
0.
0/
02
#155
0*
#156
0&
1(
1*
1/
#157
0*
#158
1*
0/
#159
0*
#160
0'
0(
1*
1/
10
b00100000 1
#161
0*
#162
1*
0/
#163
0*
#164
0)
1*
1/
00
b00000000 1
#165
0*
#166
0#
1%
1*
0/
#167
0*
#168
0$
0%
1*
1,
1.
1/
#169
0*
#170
1*
0,
0.
0/
12
#171
0*
#172
1&
1(
1*
1/
#173
0*
#174
1*
0/
#175
0*
#176
1'
0(
1*
1/
10
b00100000 1
#177
0*
#178
1*
0/
#179
0*
#180
1)
1*
1/
00
b00000000 1
#181
0*
#182
1#
1%
1*
0/
#183
0*
#184
1$
0%
1*
1,
1.
1/
#185
0*
#186
1*
0,
0.
0/
02
#187
0*
#188
0&
1(
1*
1/
#189
0*
#190
1*
0/
#191
0*
#192
0'
0(
1*
1/
10
b00100000 1
#193
0*
#194
1*
0/
#195
0*
#196
0)
1*
1/
00
b00000000 1
#197
0*
#198
0#
1%
1*
0/
#199
0*
#200
0$
0%
1*
1,
1.
1/
#201
0*
#202
1*
0,
0.
0/
12
#203
0*
#204
1&
1(
1*
1/
#205
0*
#206
1*
0/
#207
0*
#208
1'
0(
1*
1/
10
b00100000 1
#209
0*
#210
1*
0/
#211
0*
#212
1)
1*
1/
00
b00000000 1
#213
0*
#214
1#
1%
1*
0/
#215
0*
#216
1$
0%
1*
1,
1.
1/
#217
0*
#218
1*
0,
0.
0/
02
#219
0*
#220
0&
1(
1*
1/
#221
0*
#222
1*
0/
#223
0*
#224
0'
0(
1*
1/
10
b00100000 1
#225
0*
#226
1*
0/
#227
0*
#228
0)
1*
1/
00
b00000000 1
#229
0*
#230
0#
1%
1*
0/
#231
0*
#232
0$
0%
1*
1,
1.
1/
#233
0*
#234
1*
0,
0.
0/
12
#235
0*
#236
1&
1(
1*
1/
#237
0*
#238
1*
0/
#239
0*
#240
1'
0(
1*
1/
10
b00100000 1
#241
0*
#242
1*
0/
#243
0*
#244
1)
1*
1/
00
b00000000 1
#245
0*
#246
1#
1%
1*
0/
#247
0*
#248
1$
0%
1*
1,
1.
1/
#249
0*
#250
1*
0,
0.
0/
02
#251
0*
#252
0&
1(
1*
1/
#253
0*
#254
1*
0/
#255
0*
#256
0'
0(
1*
1/
10
b00100000 1
#257
0*
#258
1*
0/
#259
0*
#260
0)
1*
1/
00
b00000000 1
#261
0*
#262
0#
1%
1*
0/
#263
0*
#264
0$
0%
1*
1,
1.
1/
#265
0*
#266
1*
0,
0.
0/
12
#267
0*
#268
1&
1(
1*
1/
#269
0*
#270
1*
0/
#271
0*
#272
1'
0(
1*
1/
10
b00100000 1
#273
0*
#274
1*
0/
#275
0*
#276
1)
1*
1/
00
b00000000 1
#277
0*
#278
1#
1%
1*
0/
#279
0*
#280
1$
0%
1*
1,
1.
1/
#281
0*
#282
1*
0,
0.
0/
02
#283
0*
#284
0&
1(
1*
1/
#285
0*
#286
1*
0/
#287
0*
#288
0'
0(
1*
1/
10
b00100000 1
#289
0*
#290
1*
0/
#291
0*
#292
0)
1*
1/
00
b00000000 1
#293
0*
#294
0#
1%
1*
0/
#295
0*
#296
0$
0%
1*
1,
1.
1/
#297
0*
#298
1*
0,
0.
0/
12
#299
0*
#300
1&
1(
1*
1/
#301
0*
#302
1*
0/
#303
0*
#304
1'
0(
1*
1/
10
b00100000 1
#305
0*
#306
1*
0/
#307
0*
#308
1)
1*
1/
00
b00000000 1
#309
0*
#310
1#
1%
1*
0/
#311
0*
#312
1$
0%
1*
1,
1.
1/
#313
0*
#314
1*
0,
0.
0/
02
#315
0*
#316
0&
1(
1*
1/
#317
0*
#318
1*
0/
#319
0*
#320
0'
0(
1*
1/
10
b00100000 1
#321
0*
#322
1*
0/
#323
0*
#324
0)
1*
1/
00
b00000000 1
#325
0*
#326
0#
1%
1*
0/
#327
0*
#328
0$
0%
1*
1,
1.
1/
#329
0*
#330
1*
0,
0.
0/
12
#331
0*
#332
1&
1(
1*
1/
#333
0*
#334
1*
0/
#335
0*
#336
1'
0(
1*
1/
10
b00100000 1
#337
0*
#338
1*
0/
#339
0*
#340
1)
1*
1/
00
b00000000 1
#341
0*
#342
1#
1%
1*
0/
#343
0*
#344
1$
0%
1*
1,
1.
1/
#345
0*
#346
1*
0,
0.
0/
02
#347
0*
#348
0&
1(
1*
1/
#349
0*
#350
1*
0/
#351
0*
#352
0'
0(
1*
1/
10
b00100000 1
#353
0*
#354
1*
0/
#355
0*
#356
0)
1*
1/
00
b00000000 1
#357
0*
#358
0#
1%
1*
0/
#359
0*
#360
0$
0%
1*
1,
1.
1/
#361
0*
#362
1*
0,
0.
0/
12
#363
0*
#364
1&
1(
1*
1/
#365
0*
#366
1*
0/
#367
0*
#368
1'
0(
1*
1/
10
b00100000 1
#369
0*
#370
1*
0/
#371
0*
#372
1)
1*
1/
00
b00000000 1
#373
0*
#374
1#
1%
1*
0/
#375
0*
#376
1$
0%
1*
1,
1.
1/
#377
0*
#378
1*
0,
0.
0/
02
#379
0*
#380
0&
1(
1*
1/
#381
0*
#382
1*
0/
#383
0*
#384
0'
0(
1*
1/
10
b00100000 1
#385
0*
#386
1*
0/
#387
0*
#388
0)
1*
1/
00
b00000000 1
#389
0*
#390
0#
1%
1*
0/
#391
0*
#392
0$
0%
1*
1,
1.
1/
#393
0*
#394
1*
0,
0.
0/
12
#395
0*
#396
1&
1(
1*
1/
#397
0*
#398
1*
0/
#399
0*
#400
1'
0(
1*
1/
10
b00100000 1
#401
0*
#402
1*
0/
#403
0*
#404
1)
1*
1/
00
b00000000 1
#405
0*
#406
1#
1%
1*
0/
#407
0*
#408
1$
0%
1*
1,
1.
1/
#409
0*
#410
1*
0,
0.
0/
02
#411
0*
#412
0&
1(
1*
1/
#413
0*
#414
1*
0/
#415
0*
#416
0'
0(
1*
1/
10
b00100000 1
#417
0*
#418
1*
0/
#419
0*
#420
0)
1*
1/
00
b00000000 1
#421
0*
#422
0#
1%
1*
0/
#423
0*
#424
0$
0%
1*
1,
1.
1/
#425
0*
#426
1*
0,
0.
0/
12
#427
0*
#428
1&
1(
1*
1/
#429
0*
#430
1*
0/
#431
0*
#432
1'
0(
1*
1/
10
b00100000 1
#433
0*
#434
1*
0/
#435
0*
#436
1)
1*
1/
00
b00000000 1
#437
0*
#438
1#
1%
1*
0/
#439
0*
#440
1$
0%
1*
1,
1.
1/
#441
0*
#442
1*
0,
0.
0/
02
#443
0*
#444
0&
1(
1*
1/
#445
0*
#446
1*
0/
#447
0*
#448
0'
0(
1*
1/
10
b00100000 1
#449
0*
#450
1*
0/
#451
0*
#452
0)
1*
1/
00
b00000000 1
#453
0*
#454
0#
1%
1*
0/
#455
0*
#456
0$
0%
1*
1,
1.
1/
#457
0*
#458
1*
0,
0.
0/
12
#459
0*
#460
1&
1(
1*
1/
#461
0*
#462
1*
0/
#463
0*
#464
1'
0(
1*
1/
10
b00100000 1
#465
0*
#466
1*
0/
#467
0*
#468
1)
1*
1/
00
b00000000 1
#469
0*
#470
1#
1%
1*
0/
#471
0*
#472
1$
0%
1*
1,
1.
1/
#473
0*
#474
1*
0,
0.
0/
02
#475
0*
#476
0&
1(
1*
1/
#477
0*
#478
1*
0/
#479
0*
#480
0'
0(
1*
1/
10
b00100000 1
#481
0*
#482
1*
0/
#483
0*
#484
0)
1*
1/
00
b00000000 1
#485
0*
#486
0#
1%
1*
0/
#487
0*
#488
0$
0%
1*
1,
1.
1/
#489
0*
#490
1*
0,
0.
0/
12
#491
0*
#492
1&
1(
1*
1/
#493
0*
#494
1*
0/
#495
0*
#496
1'
0(
1*
1/
10
b00100000 1
#497
0*
#498
1*
0/
#499
0*
#500
1)
1*
1/
00
b00000000 1
#501
0*
#502
1#
1%
1*
0/
#503
0*
#504
1$
0%
1*
1,
1.
1/
#505
0*
#506
1*
0,
0.
0/
02
#507
0*
#508
0&
1(
1*
1/
#509
0*
#510
1*
0/
#511
0*
#512
0'
0(
1*
1/
10
b00100000 1
#513
0*
#514
1*
0/
#515
0*
#516
0)
1*
1/
00
b00000000 1
#517
0*
#518
0#
1%
1*
0/
#519
0*
#520
0$
0%
1*
1,
1.
1/
#521
0*
#522
1*
0,
0.
0/
12
#523
0*
#524
1&
1(
1*
1/
#525
0*
#526
1*
0/
#527
0*
#528
1'
0(
1*
1/
10
b00100000 1
#529
0*
#530
1*
0/
#531
0*
#532
1)
1*
1/
00
b00000000 1
#533
0*
#534
1#
1%
1*
0/
#535
0*
#536
1$
0%
1*
1,
1.
1/
#537
0*
#538
1*
0,
0.
0/
02
#539
0*
#540
0&
1(
1*
1/
#541
0*
#542
1*
0/
#543
0*
#544
0'
0(
1*
1/
10
b00100000 1
#545
0*
#546
1*
0/
#547
0*
#548
0)
1*
1/
00
b00000000 1
#549
0*
#550
0#
1%
1*
0/
#551
0*
#552
0$
0%
1*
1,
1.
1/
#553
0*
#554
1*
0,
0.
0/
12
#555
0*
#556
1&
1(
1*
1/
#557
0*
#558
1*
0/
#559
0*
#560
1'
0(
1*
1/
10
b00100000 1
#561
0*
#562
1*
0/
#563
0*
#564
1)
1*
1/
00
b00000000 1
#565
0*
#566
1#
1%
1*
0/
#567
0*
#568
1$
0%
1*
1,
1.
1/
#569
0*
#570
1*
0,
0.
0/
02
#571
0*
#572
0&
1(
1*
1/
#573
0*
#574
1*
0/
#575
0*
#576
0'
0(
1*
1/
10
b00100000 1
#577
0*
#578
1*
0/
#579
0*
#580
0)
1*
1/
00
b00000000 1
#581
0*
#582
0#
1%
1*
0/
#583
0*
#584
0$
0%
1*
1,
1.
1/
#585
0*
#586
1*
0,
0.
0/
12
#587
0*
#588
1&
1(
1*
1/
#589
0*
#590
1*
0/
#591
0*
#592
1'
0(
1*
1/
10
b00100000 1
#593
0*
#594
1*
0/
#595
0*
#596
1)
1*
1/
00
b00000000 1
#597
0*
#598
1#
1%
1*
0/
#599
0*
#600
1$
0%
1*
1,
1.
1/
#601
0*
#602
1*
0,
0.
0/
02
#603
0*
#604
0&
1(
1*
1/
#605
0*
#606
1*
0/
#607
0*
#608
0'
0(
1*
1/
10
b00100000 1
#609
0*
#610
1*
0/
#611
0*
#612
0)
1*
1/
00
b00000000 1
#613
0*
#614
0#
1%
1*
0/
#615
0*
#616
0$
0%
1*
1,
1.
1/
#617
0*
#618
1*
0,
0.
0/
12
#619
0*
#620
1&
1(
1*
1/
#621
0*
#622
1*
0/
#623
0*
#624
1'
0(
1*
1/
10
b00100000 1
#625
0*
#626
1*
0/
#627
0*
#628
1)
1*
1/
00
b00000000 1
#629
0*
#630
1#
1%
1*
0/
#631
0*
#632
1$
0%
1*
1,
1.
1/
#633
0*
#634
1*
0,
0.
0/
02
#635
0*
#636
0&
1(
1*
1/
#637
0*
#638
1*
0/
#639
0*
#640
0'
0(
1*
1/
10
b00100000 1
#641
0*
#642
1*
0/
#643
0*
#644
0)
1*
1/
00
b00000000 1
#645
0*
#646
0#
1%
1*
0/
#647
0*
#648
0$
0%
1*
1,
1.
1/
#649
0*
#650
1*
0,
0.
0/
12
#651
0*
#652
1&
1(
1*
1/
#653
0*
#654
1*
0/
#655
0*
#656
1'
0(
1*
1/
10
b00100000 1
#657
0*
#658
1*
0/
#659
0*
#660
1)
1*
1/
00
b00000000 1
#661
0*
#662
1#
1%
1*
0/
#663
0*
#664
1$
0%
1*
1,
1.
1/
#665
0*
#666
1*
0,
0.
0/
02
#667
0*
#668
0&
1(
1*
1/
#669
0*
#670
1*
0/
#671
0*
#672
0'
0(
1*
1/
10
b00100000 1
#673
0*
#674
1*
0/
#675
0*
#676
0)
1*
1/
00
b00000000 1
#677
0*
#678
0#
1%
1*
0/
#679
0*
#680
0$
0%
1*
1,
1.
1/
#681
0*
#682
1*
0,
0.
0/
12
#683
0*
#684
1&
1(
1*
1/
#685
0*
#686
1*
0/
#687
0*
#688
1'
0(
1*
1/
10
b00100000 1
#689
0*
#690
1*
0/
#691
0*
#692
1)
1*
1/
00
b00000000 1
#693
0*
#694
1#
1%
1*
0/
#695
0*
#696
1$
0%
1*
1,
1.
1/
#697
0*
#698
1*
0,
0.
0/
02
#699
0*
#700
0&
1(
1*
1/
#701
0*
#702
1*
0/
#703
0*
#704
0'
0(
1*
1/
10
b00100000 1
#705
0*
#706
1*
0/
#707
0*
#708
0)
1*
1/
00
b00000000 1
#709
0*
#710
0#
1%
1*
0/
#711
0*
#712
0$
0%
1*
1,
1.
1/
#713
0*
#714
1*
0,
0.
0/
12
#715
0*
#716
1&
1(
1*
1/
#717
0*
#718
1*
0/
#719
0*
#720
1'
0(
1*
1/
10
b00100000 1
#721
0*
#722
1*
0/
#723
0*
#724
1)
1*
1/
00
b00000000 1
#725
0*
#726
1#
1%
1*
0/
#727
0*
#728
1$
0%
1*
1,
1.
1/
#729
0*
#730
1*
0,
0.
0/
02
#731
0*
#732
0&
1(
1*
1/
#733
0*
#734
1*
0/
#735
0*
#736
0'
0(
1*
1/
10
b00100000 1
#737
0*
#738
1*
0/
#739
0*
#740
0)
1*
1/
00
b00000000 1
#741
0*
#742
0#
1%
1*
0/
#743
0*
#744
0$
0%
1*
1,
1.
1/
#745
0*
#746
1*
0,
0.
0/
12
#747
0*
#748
1&
1(
1*
1/
#749
0*
#750
1*
0/
#751
0*
#752
1'
0(
1*
1/
10
b00100000 1
#753
0*
#754
1*
0/
#755
0*
#756
1)
1*
1/
00
b00000000 1
#757
0*
#758
1#
1%
1*
0/
#759
0*
#760
1$
0%
1*
1,
1.
1/
#761
0*
#762
1*
0,
0.
0/
02
#763
0*
#764
0&
1(
1*
1/
#765
0*
#766
1*
0/
#767
0*
#768
0'
0(
1*
1/
10
b00100000 1
#769
0*
#770
1*
0/
#771
0*
#772
0)
1*
1/
00
b00000000 1
#773
0*
#774
0#
1%
1*
0/
#775
0*
#776
0$
0%
1*
1,
1.
1/
#777
0*
#778
1*
0,
0.
0/
12
#779
0*
#780
1&
1(
1*
1/
#781
0*
#782
1*
0/
#783
0*
#784
1'
0(
1*
1/
10
b00100000 1
#785
0*
#786
1*
0/
#787
0*
#788
1)
1*
1/
00
b00000000 1
#789
0*
#790
1#
1%
1*
0/
#791
0*
#792
1$
0%
1*
1,
1.
1/
#793
0*
#794
1*
0,
0.
0/
02
#795
0*
#796
0&
1(
1*
1/
