CDC/pulse_sync.v
`timescale 1ns/1ps

module pulse_sync(
    input           clka,
    input           rst_n,
    input           din,
    input           clkb,
    output  reg     dout
);

reg toggle;
always @(posedge clka or negedge rst_n) begin
    if(!rst_n)
        toggle <= 1'b0;
    else if(din)
        toggle <= ~toggle;
    else
        toggle <= toggle;
end

reg toggle_sync1;
reg toggle_sync2;
reg toggle_sync3;
always @(posedge clkb or negedge rst_n) begin
    if(!rst_n) begin
        toggle_sync1 <= 1'b0;
        toggle_sync2 <= 1'b0;
        toggle_sync3 <= 1'b0;
    end else begin
        toggle_sync1 <= toggle;
        toggle_sync2 <= toggle_sync1;
        toggle_sync3 <= toggle_sync2;
    end
end

always @(posedge clkb or negedge rst_n) begin
    if(!rst_n)
        dout <= 1'b0;
    else
        dout <= toggle_sync3 ^ toggle_sync2; 
end



endmodule

CDC/waveform.vcd
$version Generated by VerilatedVcd $end
$timescale 1ps $end

 $scope module TOP $end
  $var wire  1 & clka $end
  $var wire  1 ) clkb $end
  $var wire  1 ( din $end
  $var wire  1 * dout $end
  $var wire  1 ' rst_n $end
  $scope module pulse_sync $end
   $var wire  1 & clka $end
   $var wire  1 ) clkb $end
   $var wire  1 ( din $end
   $var wire  1 * dout $end
   $var wire  1 ' rst_n $end
   $var wire  1 + toggle $end
   $var wire  1 # toggle_sync1 $end
   $var wire  1 $ toggle_sync2 $end
   $var wire  1 % toggle_sync3 $end
  $upscope $end
 $upscope $end
$enddefinitions $end


#0
0#
0$
0%
1&
1'
0(
1)
0*
0+
#1
0&
#2
1&
0'
0)
#3
0&
#4
1&
1)
#5
0&
#6
1&
1'
0)
#7
0&
#8
1&
1(
1)
#9
0&
#10
1&
0(
0)
1+
#11
0&
#12
1#
1&
1)
#13
0&
#14
1&
0)
#15
0&
#16
1$
1&
1)
#17
0&
#18
1&
0)
#19
0&
#20
1%
1&
1)
1*
#21
0&
#22
1&
0)
#23
0&
#24
1&
1)
0*
#25
0&
#26
1&
0)
#27
0&
#28
1&
1)
#29
0&
#30
1&
1(
0)
#31
0&
#32
1&
0(
1)
0+
#33
0&
#34
1&
0)
#35
0&
#36
0#
1&
1)
#37
0&
#38
1&
0)
#39
0&
#40
0$
1&
1)
#41
0&
#42
1&
0)
#43
0&
#44
0%
1&
1)
1*
#45
0&
#46
1&
0)
#47
0&
#48
1&
1)
0*
