位宽宽窄变换/wide2narrow.v
module wide2narrow(
    input               clk,
    input               rst_n,
    input   [7:0]       wide_din,

    output  [3:0]       narrow_dout
);

reg     flag;   // 其实是clk的二分频
always @(posedge clk or negedge rst_n) begin
    if(!rst_n)
        flag <= 1'b0;
    else
        flag <= ~flag;
end

reg     [7:0]   wide_din_sync;
always @(posedge flag or negedge rst_n) begin
    if(!rst_n)
        wide_din_sync <= 'd0;
    else
        wide_din_sync <= wide_din;
end

assign narrow_dout = flag ? wide_din_sync[7:4] : wide_din_sync[3:0];


endmodule

位宽宽窄变换/waveform.vcd
$version Generated by VerilatedVcd $end
$timescale 1ps $end

 $scope module TOP $end
  $var wire  1 # clk $end
  $var wire  4 & narrow_dout [3:0] $end
  $var wire  1 $ rst_n $end
  $var wire  8 % wide_din [7:0] $end
  $scope module wide2narrow $end
   $var wire  1 # clk $end
   $var wire  1 ' flag $end
   $var wire  4 & narrow_dout [3:0] $end
   $var wire  1 $ rst_n $end
   $var wire  8 % wide_din [7:0] $end
   $var wire  8 ( wide_din_sync [7:0] $end
  $upscope $end
 $upscope $end
$enddefinitions $end


#0
1#
1$
b00000000 %
b0000 &
0'
b00000000 (
#1
0#
#2
1#
0$
#3
0#
#4
1#
#5
0#
#6
1#
1$
1'
#7
0#
#8
1#
0'
#9
0#
#10
1#
1'
#11
0#
#12
1#
0'
#13
0#
#14
1#
1'
#15
0#
#16
1#
0'
#17
0#
#18
1#
1'
#19
0#
#20
1#
0'
#21
0#
#22
1#
1'
#23
0#
#24
1#
0'
#25
0#
#26
1#
1'
#27
0#
#28
1#
b11110000 %
0'
#29
0#
#30
1#
b01100101 %
b1111 &
1'
b11110000 (
#31
0#
#32
1#
b01011010 %
b0000 &
0'
#33
0#
#34
1#
b01110011 %
b0101 &
1'
b01011010 (
#35
0#
#36
1#
b11000100 %
b1010 &
0'
#37
0#
#38
1#
b11010010 %
b1100 &
1'
b11000100 (
#39
0#
#40
1#
b00011111 %
b0100 &
0'
#41
0#
#42
1#
b10111101 %
b0001 &
1'
b00011111 (
#43
0#
#44
1#
b00000000 %
b1111 &
0'
#45
0#
#46
1#
b0000 &
1'
b00000000 (
#47
0#
#48
1#
0'
#49
0#
#50
1#
1'
#51
0#
#52
1#
0'
#53
0#
#54
1#
1'
#55
0#
#56
1#
0'
#57
0#
#58
1#
1'
#59
0#
#60
1#
0'
#61
0#
#62
1#
1'
#63
0#
#64
1#
0'
#65
0#
#66
1#
1'
#67
0#
#68
1#
0'
#69
0#
#70
1#
1'
#71
0#
#72
1#
0'
#73
0#
#74
1#
1'
#75
0#
#76
1#
0'
#77
0#
#78
1#
1'
#79
0#
#80
1#
0'
#81
0#
#82
1#
1'
#83
0#
#84
1#
0'
#85
0#
#86
1#
1'
#87
0#
#88
1#
0'
#89
0#
#90
1#
1'
#91
0#
#92
1#
0'
#93
0#
#94
1#
1'
#95
0#
#96
1#
0'
#97
0#
#98
1#
1'
#99
0#
#100
1#
0'
#101
0#
#102
1#
1'
#103
0#
#104
1#
0'
#105
0#
#106
1#
1'
#107
0#
#108
1#
0'
#109
0#
#110
1#
1'
#111
0#
#112
1#
0'
#113
0#
#114
1#
1'
#115
0#
#116
1#
0'
#117
0#
#118
1#
1'
#119
0#
#120
1#
0'
#121
0#
#122
1#
1'
#123
0#
#124
1#
0'
#125
0#
#126
1#
1'
#127
0#
#128
1#
0'
#129
0#
#130
1#
1'
#131
0#
#132
1#
0'
#133
0#
#134
1#
1'
#135
0#
#136
1#
0'
#137
0#
#138
1#
1'
#139
0#
#140
1#
0'
#141
0#
#142
1#
1'
#143
0#
#144
1#
0'
#145
0#
#146
1#
1'
#147
0#
#148
1#
0'
#149
0#
#150
1#
1'
#151
0#
#152
1#
0'
#153
0#
#154
1#
1'
#155
0#
#156
1#
0'
#157
0#
#158
1#
1'
#159
0#
#160
1#
0'
#161
0#
#162
1#
1'
#163
0#
#164
1#
0'
#165
0#
#166
1#
1'
#167
0#
#168
1#
0'
#169
0#
#170
1#
1'
#171
0#
#172
1#
0'
#173
0#
#174
1#
1'
#175
0#
#176
1#
0'
#177
0#
#178
1#
1'
#179
0#
#180
1#
0'
#181
0#
#182
1#
1'
#183
0#
#184
1#
0'
#185
0#
#186
1#
1'
#187
0#
#188
1#
0'
#189
0#
#190
1#
1'
#191
0#
#192
1#
0'
#193
0#
#194
1#
1'
#195
0#
#196
1#
0'
#197
0#
#198
1#
1'
#199
0#
#200
1#
0'
#201
0#
#202
1#
1'
#203
0#
#204
1#
0'
#205
0#
#206
1#
1'
#207
0#
#208
1#
0'
#209
0#
#210
1#
1'
#211
0#
#212
1#
0'
#213
0#
#214
1#
1'
#215
0#
#216
1#
0'
#217
0#
#218
1#
1'
#219
0#
#220
1#
0'
#221
0#
#222
1#
1'
#223
0#
#224
1#
0'
#225
0#
#226
1#
1'
#227
0#
#228
1#
0'
#229
0#
#230
1#
1'
#231
0#
#232
1#
0'
#233
0#
#234
1#
1'
#235
0#
#236
1#
0'
#237
0#
#238
1#
1'
#239
0#
#240
1#
0'
#241
0#
#242
1#
1'
#243
0#
#244
1#
0'
#245
0#
#246
1#
1'
#247
0#
#248
1#
0'
#249
0#
#250
1#
1'
#251
0#
#252
1#
0'
#253
0#
#254
1#
1'
#255
0#
#256
1#
0'
#257
0#
#258
1#
1'
#259
0#
#260
1#
0'
#261
0#
#262
1#
1'
#263
0#
#264
1#
0'
#265
0#
#266
1#
1'
#267
0#
#268
1#
0'
#269
0#
#270
1#
1'
#271
0#
#272
1#
0'
#273
0#
#274
1#
1'
#275
0#
#276
1#
0'
#277
0#
#278
1#
1'
#279
0#
#280
1#
0'
#281
0#
#282
1#
1'
#283
0#
#284
1#
0'
#285
0#
#286
1#
1'
#287
0#
#288
1#
0'
#289
0#
#290
1#
1'
#291
0#
#292
1#
0'
#293
0#
#294
1#
1'
#295
0#
#296
1#
0'
#297
0#
#298
1#
1'
