串并转换/width_12to16.v
module width_12to16(
    input           clk,
    input           rst_n,
    input   [11:0]  din,
    input           din_vld,
    input           din_vld_last,

    output  reg [15:0]  dout,
    output  reg         dout_vld
    //output  reg         dout_vld_last
);

reg [11:0]  din_reg;
always @(posedge clk or negedge rst_n) begin
    if(!rst_n)
        din_reg <= 'd0;
    else if(din_vld)
        din_reg <= din;
    else    
        din_reg <= din_reg;
end

reg [1:0]   din_vld_cnt;
always @(posedge clk or negedge rst_n) begin
    if(!rst_n)
        din_vld_cnt <= 'd0;
    else if(din_vld)
        din_vld_cnt <= din_vld_cnt + 1'b1;
end

always @(posedge clk or negedge rst_n) begin
    if(!rst_n)
        dout <= 'd0;
    else if(din_vld) begin
        case(din_vld_cnt)
            2'b01: dout <= {din[3:0],din_reg};
            2'b10: dout <= {din[7:0],din_reg[11:4]};
            2'b11: dout <= {din,din_reg[11:8]};
            default: dout <= dout;
        endcase
    end
end

always @(posedge clk or negedge rst_n) begin
    if(!rst_n)
        dout_vld <= 'd0;
    else if(din_vld && ((din_vld_cnt == 'd1) || (din_vld_cnt == 'd2) || (din_vld_cnt == 'd3)))
        dout_vld <= 1'b1;
    else
        dout_vld <= 1'b0;
end

endmodule

串并转换/waveform.vcd
$version Generated by VerilatedVcd $end
$timescale 1ps $end

 $scope module TOP $end
  $var wire  1 # clk $end
  $var wire 12 % din [11:0] $end
  $var wire  1 & din_vld $end
  $var wire  1 ' din_vld_last $end
  $var wire 16 ( dout [15:0] $end
  $var wire  1 ) dout_vld $end
  $var wire  1 $ rst_n $end
  $scope module width_12to16 $end
   $var wire  1 # clk $end
   $var wire 12 % din [11:0] $end
   $var wire 12 * din_reg [11:0] $end
   $var wire  1 & din_vld $end
   $var wire  2 + din_vld_cnt [1:0] $end
   $var wire  1 ' din_vld_last $end
   $var wire 16 ( dout [15:0] $end
   $var wire  1 ) dout_vld $end
   $var wire  1 $ rst_n $end
  $upscope $end
 $upscope $end
$enddefinitions $end


#0
1#
1$
b000000000000 %
0&
0'
b0000000000000000 (
0)
b000000000000 *
b00 +
#1
0#
0$
#2
1#
#3
0#
#4
1#
#5
0#
#6
1#
1$
#7
0#
#8
1#
#9
0#
#10
1#
#11
0#
#12
1#
#13
0#
#14
1#
#15
0#
#16
1#
#17
0#
#18
1#
#19
0#
#20
1#
#21
0#
#22
1#
#23
0#
#24
1#
#25
0#
#26
1#
#27
0#
#28
1#
#29
0#
#30
1#
#31
0#
#32
1#
#33
0#
#34
1#
#35
0#
#36
1#
#37
0#
#38
1#
#39
0#
#40
1#
b000000001100 %
1&
#41
0#
#42
1#
0&
b000000001100 *
b01 +
#43
0#
#44
1#
b000000010101 %
1&
#45
0#
#46
1#
0&
b0101000000001100 (
1)
b000000010101 *
b10 +
#47
0#
#48
1#
0)
#49
0#
#50
1#
#51
0#
#52
1#
#53
0#
#54
1#
b000000010001 %
1&
#55
0#
#56
1#
0&
b0001000100000001 (
1)
b000000010001 *
b11 +
#57
0#
#58
1#
0)
#59
0#
#60
1#
#61
0#
#62
1#
#63
0#
#64
1#
#65
0#
#66
1#
#67
0#
#68
1#
#69
0#
#70
1#
#71
0#
#72
1#
#73
0#
#74
1#
#75
0#
#76
1#
#77
0#
#78
1#
#79
0#
#80
1#
b000000000010 %
1&
#81
0#
#82
1#
0&
b0000000000100000 (
1)
b000000000010 *
b00 +
#83
0#
#84
1#
0)
#85
0#
#86
1#
#87
0#
#88
1#
#89
0#
#90
1#
b000010111011 %
1&
#91
0#
#92
1#
0&
b000010111011 *
b01 +
#93
0#
#94
1#
#95
0#
#96
1#
#97
0#
#98
1#
b000010011110 %
1&
#99
0#
#100
1#
0&
b1110000010111011 (
1)
b000010011110 *
b10 +
#101
0#
#102
1#
0)
#103
0#
#104
1#
#105
0#
#106
1#
#107
0#
#108
1#
#109
0#
#110
1#
b000001100011 %
1&
#111
0#
#112
1#
0&
b0110001100001001 (
1)
b000001100011 *
b11 +
#113
0#
#114
1#
0)
