div_M_N/div_m_n.v
`timescale 1ns/1ns

module div_m_n #(parameter 
    M_N = 8'd87, 
    c89 = 8'd24, 
    div_e = 5'd8,
    div_o = 5'd9
)(
    input  wire clk,
    input  wire rst_n,
    output wire clk_out
);

localparam CNT_WIDTH = $clog2(M_N);
localparam CNT2_WIDTH = $clog2(c89);

reg [CNT_WIDTH-1:0]     cnt_clk;
reg [CNT2_WIDTH-1:0]    cnt_div;
reg                     div_flag;

/* verilator lint_off WIDTHEXPAND */

always @(posedge clk or negedge rst_n) begin
    if(!rst_n)
        cnt_clk <= 'd0;
    else if(cnt_clk == M_N-1)
        cnt_clk <= 'd0;
    else
        cnt_clk <= cnt_clk + 1'b1;
end

always @(posedge clk or negedge rst_n) begin
    if(!rst_n)
        cnt_div <= 'd0;
    else if(~div_flag) begin
        if(cnt_div == div_e-1)
            cnt_div <= 'd0;
        else
            cnt_div <= cnt_div + 1'b1;
    end
    else begin
        if(cnt_div == div_o-1)
            cnt_div <= 'd0;
        else
            cnt_div <= cnt_div + 1'b1;
    end
end

always @(posedge clk or negedge rst_n) begin
    if(!rst_n)
        div_flag <= 1'b0;
    else if(cnt_clk == (M_N-1) || cnt_clk == (c89-1))
        div_flag <= ~div_flag;
    else
        div_flag <= div_flag;
end

reg clk_out_r;
always @(posedge clk or negedge rst_n) begin
    if(!rst_n)
        clk_out_r <= 'd0;
    else if(~div_flag) 
        clk_out_r <= (cnt_div <= (div_e>>2)+1);
    else
        clk_out_r <= (cnt_div <= (div_o>>2)+1);
end

assign clk_out = clk_out_r;

endmodule

div_M_N/waveform.vcd
$version Generated by VerilatedVcd $end
$timescale 1ns $end

 $scope module TOP $end
  $var wire  1 ' clk $end
  $var wire  1 ) clk_out $end
  $var wire  1 ( rst_n $end
  $scope module div_m_n $end
   $var wire 32 / CNT2_WIDTH [31:0] $end
   $var wire 32 . CNT_WIDTH [31:0] $end
   $var wire  8 * M_N [7:0] $end
   $var wire  8 + c89 [7:0] $end
   $var wire  1 ' clk $end
   $var wire  1 ) clk_out $end
   $var wire  1 & clk_out_r $end
   $var wire  7 # cnt_clk [6:0] $end
   $var wire  5 $ cnt_div [4:0] $end
   $var wire  5 , div_e [4:0] $end
   $var wire  1 % div_flag $end
   $var wire  5 - div_o [4:0] $end
   $var wire  1 ( rst_n $end
  $upscope $end
 $upscope $end
$enddefinitions $end


#0
b0000000 #
b00000 $
0%
0&
1'
1(
0)
b01010111 *
b00011000 +
b01000 ,
b01001 -
b00000000000000000000000000000111 .
b00000000000000000000000000000101 /
#1
0'
0(
#2
1'
#3
0'
#4
1'
#5
0'
#6
b0000001 #
b00001 $
1&
1'
1(
1)
#7
0'
#8
b0000010 #
b00010 $
1'
#9
0'
#10
b0000011 #
b00011 $
1'
#11
0'
#12
b0000100 #
b00100 $
1'
#13
0'
#14
b0000101 #
b00101 $
0&
1'
0)
#15
0'
#16
b0000110 #
b00110 $
1'
#17
0'
#18
b0000111 #
b00111 $
1'
#19
0'
#20
b0001000 #
b00000 $
1'
#21
0'
#22
b0001001 #
b00001 $
1&
1'
1)
#23
0'
#24
b0001010 #
b00010 $
1'
#25
0'
#26
b0001011 #
b00011 $
1'
#27
0'
#28
b0001100 #
b00100 $
1'
#29
0'
#30
b0001101 #
b00101 $
0&
1'
0)
#31
0'
#32
b0001110 #
b00110 $
1'
#33
0'
#34
b0001111 #
b00111 $
1'
#35
0'
#36
b0010000 #
b00000 $
1'
#37
0'
#38
b0010001 #
b00001 $
1&
1'
1)
#39
0'
#40
b0010010 #
b00010 $
1'
#41
0'
#42
b0010011 #
b00011 $
1'
#43
0'
#44
b0010100 #
b00100 $
1'
#45
0'
#46
b0010101 #
b00101 $
0&
1'
0)
#47
0'
#48
b0010110 #
b00110 $
1'
#49
0'
#50
b0010111 #
b00111 $
1'
#51
0'
#52
b0011000 #
b00000 $
1%
1'
#53
0'
#54
b0011001 #
b00001 $
1&
1'
1)
#55
0'
#56
b0011010 #
b00010 $
1'
#57
0'
#58
b0011011 #
b00011 $
1'
#59
0'
#60
b0011100 #
b00100 $
1'
#61
0'
#62
b0011101 #
b00101 $
0&
1'
0)
#63
0'
#64
b0011110 #
b00110 $
1'
#65
0'
#66
b0011111 #
b00111 $
1'
#67
0'
#68
b0100000 #
b01000 $
1'
#69
0'
#70
b0100001 #
b00000 $
1'
#71
0'
#72
b0100010 #
b00001 $
1&
1'
1)
#73
0'
#74
b0100011 #
b00010 $
1'
#75
0'
#76
b0100100 #
b00011 $
1'
#77
0'
#78
b0100101 #
b00100 $
1'
#79
0'
#80
b0100110 #
b00101 $
0&
1'
0)
#81
0'
#82
b0100111 #
b00110 $
1'
#83
0'
#84
b0101000 #
b00111 $
1'
#85
0'
#86
b0101001 #
b01000 $
1'
#87
0'
#88
b0101010 #
b00000 $
1'
#89
0'
#90
b0101011 #
b00001 $
1&
1'
1)
#91
0'
#92
b0101100 #
b00010 $
1'
#93
0'
#94
b0101101 #
b00011 $
1'
#95
0'
#96
b0101110 #
b00100 $
1'
#97
0'
#98
b0101111 #
b00101 $
0&
1'
0)
#99
0'
#100
b0110000 #
b00110 $
1'
#101
0'
#102
b0110001 #
b00111 $
1'
#103
0'
#104
b0110010 #
b01000 $
1'
#105
0'
#106
b0110011 #
b00000 $
1'
#107
0'
#108
b0110100 #
b00001 $
1&
1'
1)
#109
0'
#110
b0110101 #
b00010 $
1'
#111
0'
#112
b0110110 #
b00011 $
1'
#113
0'
#114
b0110111 #
b00100 $
1'
#115
0'
#116
b0111000 #
b00101 $
0&
1'
0)
#117
0'
#118
b0111001 #
b00110 $
1'
#119
0'
#120
b0111010 #
b00111 $
1'
#121
0'
#122
b0111011 #
b01000 $
1'
#123
0'
#124
b0111100 #
b00000 $
1'
#125
0'
#126
b0111101 #
b00001 $
1&
1'
1)
#127
0'
#128
b0111110 #
b00010 $
1'
#129
0'
#130
b0111111 #
b00011 $
1'
#131
0'
#132
b1000000 #
b00100 $
1'
#133
0'
#134
b1000001 #
b00101 $
0&
1'
0)
#135
0'
#136
b1000010 #
b00110 $
1'
#137
0'
#138
b1000011 #
b00111 $
1'
#139
0'
#140
b1000100 #
b01000 $
1'
#141
0'
#142
b1000101 #
b00000 $
1'
#143
0'
#144
b1000110 #
b00001 $
1&
1'
1)
#145
0'
#146
b1000111 #
b00010 $
1'
#147
0'
#148
b1001000 #
b00011 $
1'
#149
0'
#150
b1001001 #
b00100 $
1'
#151
0'
#152
b1001010 #
b00101 $
0&
1'
0)
#153
0'
#154
b1001011 #
b00110 $
1'
#155
0'
#156
b1001100 #
b00111 $
1'
#157
0'
#158
b1001101 #
b01000 $
1'
#159
0'
#160
b1001110 #
b00000 $
1'
#161
0'
#162
b1001111 #
b00001 $
1&
1'
1)
#163
0'
#164
b1010000 #
b00010 $
1'
#165
0'
#166
b1010001 #
b00011 $
1'
#167
0'
#168
b1010010 #
b00100 $
1'
#169
0'
#170
b1010011 #
b00101 $
0&
1'
0)
#171
0'
#172
b1010100 #
b00110 $
1'
#173
0'
#174
b1010101 #
b00111 $
1'
#175
0'
#176
b1010110 #
b01000 $
1'
#177
0'
#178
b0000000 #
b00000 $
0%
1'
#179
0'
#180
b0000001 #
b00001 $
1&
1'
1)
#181
0'
#182
b0000010 #
b00010 $
1'
#183
0'
#184
b0000011 #
b00011 $
1'
#185
0'
#186
b0000100 #
b00100 $
1'
#187
0'
#188
b0000101 #
b00101 $
0&
1'
0)
#189
0'
#190
b0000110 #
b00110 $
1'
#191
0'
#192
b0000111 #
b00111 $
1'
#193
0'
#194
b0001000 #
b00000 $
1'
#195
0'
#196
b0001001 #
b00001 $
1&
1'
1)
#197
0'
#198
b0001010 #
b00010 $
1'
#199
0'
#200
b0001011 #
b00011 $
1'
#201
0'
#202
b0001100 #
b00100 $
1'
#203
0'
#204
b0001101 #
b00101 $
0&
1'
0)
#205
0'
#206
b0001110 #
b00110 $
1'
#207
0'
#208
b0001111 #
b00111 $
1'
#209
0'
#210
b0010000 #
b00000 $
1'
#211
0'
#212
b0010001 #
b00001 $
1&
1'
1)
#213
0'
#214
b0010010 #
b00010 $
1'
#215
0'
#216
b0010011 #
b00011 $
1'
#217
0'
#218
b0010100 #
b00100 $
1'
#219
0'
#220
b0010101 #
b00101 $
0&
1'
0)
#221
0'
#222
b0010110 #
b00110 $
1'
#223
0'
#224
b0010111 #
b00111 $
1'
#225
0'
#226
b0011000 #
b00000 $
1%
1'
#227
0'
#228
b0011001 #
b00001 $
1&
1'
1)
#229
0'
#230
b0011010 #
b00010 $
1'
#231
0'
#232
b0011011 #
b00011 $
1'
#233
0'
#234
b0011100 #
b00100 $
1'
#235
0'
#236
b0011101 #
b00101 $
0&
1'
0)
#237
0'
#238
b0011110 #
b00110 $
1'
#239
0'
#240
b0011111 #
b00111 $
1'
#241
0'
#242
b0100000 #
b01000 $
1'
#243
0'
#244
b0100001 #
b00000 $
1'
#245
0'
#246
b0100010 #
b00001 $
1&
1'
1)
#247
0'
#248
b0100011 #
b00010 $
1'
#249
0'
#250
b0100100 #
b00011 $
1'
#251
0'
#252
b0100101 #
b00100 $
1'
#253
0'
#254
b0100110 #
b00101 $
0&
1'
0)
#255
0'
#256
b0100111 #
b00110 $
1'
#257
0'
#258
b0101000 #
b00111 $
1'
#259
0'
#260
b0101001 #
b01000 $
1'
#261
0'
#262
b0101010 #
b00000 $
1'
#263
0'
#264
b0101011 #
b00001 $
1&
1'
1)
#265
0'
#266
b0101100 #
b00010 $
1'
#267
0'
#268
b0101101 #
b00011 $
1'
#269
0'
#270
b0101110 #
b00100 $
1'
#271
0'
#272
b0101111 #
b00101 $
0&
1'
0)
#273
0'
#274
b0110000 #
b00110 $
1'
#275
0'
#276
b0110001 #
b00111 $
1'
#277
0'
#278
b0110010 #
b01000 $
1'
#279
0'
#280
b0110011 #
b00000 $
1'
#281
0'
#282
b0110100 #
b00001 $
1&
1'
1)
#283
0'
#284
b0110101 #
b00010 $
1'
#285
0'
#286
b0110110 #
b00011 $
1'
#287
0'
#288
b0110111 #
b00100 $
1'
#289
0'
#290
b0111000 #
b00101 $
0&
1'
0)
#291
0'
#292
b0111001 #
b00110 $
1'
#293
0'
#294
b0111010 #
b00111 $
1'
#295
0'
#296
b0111011 #
b01000 $
1'
#297
0'
#298
b0111100 #
b00000 $
1'
