round_robin_arbiter/round_robin_arbiter.v
`timescale 1ns/1ns

module round_robin_arbiter#(parameter
    N   =   16
)(
    input               clk,
    input               rst_n,
    input   [N-1:0]     req,
    output  reg [N-1:0] grant
);

reg     [N-1:0]     pointer_reg; // 优先级寄存器

wire    [N-1:0]     req_masked;
assign req_masked = req & pointer_reg;

/* verilator lint_off UNOPTFLAT */
wire    [N-1:0]     mask_higher_pri_reqs;
assign mask_higher_pri_reqs[N-1:1] = mask_higher_pri_reqs[N-2:0] | req_masked[N-2:0];
assign mask_higher_pri_reqs[0] = 1'b0;

wire    [N-1:0]     grant_masked;
wire grant_masked = req_masked & (~mask_higher_pri_reqs);

wire    [N-1:0]     unmask_higher_pri_reqs;
assign unmask_higher_pri_reqs[N-1:1] = unmask_higher_pri_reqs[N-2:0] | req[N-2:0];
assign unmask_higher_pri_reqs[0] = 1'b0;

wire    [N-1:0]     grant_unmasked;
assign grant_unmasked = req & ~unmask_higher_pri_reqs;

wire    no_req_masked;
assign no_req_masked = ~(|req_masked);

wire    [N-1:0]     grant_s;
assign  grant_s = grant_masked | ({N{no_req_masked}} & grant_unmasked);

always @(posedge clk or negedge rst_n) begin
    if(!rst_n)
        grant <= 'd0;
    else
        grant <= grant_s;
end

always @(posedge clk or negedge rst_n) begin
    if(!rst_n)
        pointer_reg <= {N{1'b1}};
    else begin
        if(|req_masked)
            pointer_reg <= mask_higher_pri_reqs;
        else if(|req)
            pointer_reg <= unmask_higher_pri_reqs;
        else
            pointer_reg <= pointer_reg;
    end
end

endmodule

round_robin_arbiter/waveform.vcd
$version Generated by VerilatedVcd $end
$timescale 1ns $end

 $scope module TOP $end
  $var wire  1 # clk $end
  $var wire  4 & grant [3:0] $end
  $var wire  4 % req [3:0] $end
  $var wire  1 $ rst_n $end
  $scope module round_robin_arbiter $end
   $var wire 32 / N [31:0] $end
   $var wire  1 # clk $end
   $var wire  4 & grant [3:0] $end
   $var wire  4 * grant_masked [3:0] $end
   $var wire  4 . grant_s [3:0] $end
   $var wire  4 , grant_unmasked [3:0] $end
   $var wire  4 ) mask_higher_pri_reqs [3:0] $end
   $var wire  1 - no_req_masked $end
   $var wire  4 ' pointer_reg [3:0] $end
   $var wire  4 % req [3:0] $end
   $var wire  4 ( req_masked [3:0] $end
   $var wire  1 $ rst_n $end
   $var wire  4 + unmask_higher_pri_reqs [3:0] $end
  $upscope $end
 $upscope $end
$enddefinitions $end


#0
1#
1$
b0000 %
b0000 &
b0000 '
b0000 (
b0000 )
b0000 *
b0000 +
b0000 ,
1-
b0000 .
b00000000000000000000000000000100 /
#1
0#
0$
b1111 '
#2
1#
#3
0#
#4
1#
#5
0#
#6
1#
1$
#7
0#
#8
1#
#9
0#
#10
1#
b0110 %
b0110 ,
b0110 .
#11
0#
b0110 (
b1100 )
b0010 *
b1100 +
b0010 ,
0-
b0010 .
#12
1#
b0111 %
b0010 &
b1100 '
b0100 (
b1000 )
b0100 *
b0011 ,
b0100 .
#13
0#
b1110 +
b0001 ,
#14
1#
b0100 %
b0100 &
b1000 '
b0000 (
b0000 )
b0000 *
b0000 ,
1-
b0000 .
#15
0#
b1000 +
b0100 ,
b0100 .
#16
1#
b0001 %
b0001 ,
b0001 .
#17
0#
b1110 +
#18
1#
b0011 %
b0001 &
b1110 '
#19
0#
b0010 (
b1100 )
b0010 *
0-
b0010 .
#20
1#
b0010 &
b1100 '
b0000 (
b0000 )
b0000 *
1-
b0001 .
#21
0#
#22
1#
b1111 %
b0001 &
b1110 '
b0010 (
b1100 )
b0010 *
0-
b0010 .
#23
0#
b1110 (
#24
1#
b1010 %
b0010 &
b1100 '
b1100 (
b1000 )
b0100 *
b0000 ,
b0100 .
#25
0#
b1000 (
b0000 )
b1000 *
b1100 +
b0010 ,
b1000 .
#26
1#
b0101 %
b1000 &
b0000 '
b0000 (
b0000 *
b0001 ,
1-
b0001 .
#27
0#
b1110 +
#28
1#
b0001 &
b1110 '
b0100 (
b1000 )
b0100 *
0-
b0100 .
#29
0#
#30
1#
b0100 &
b1000 '
b0000 (
b0000 )
b0000 *
1-
b0001 .
#31
0#
#32
1#
b0001 &
b1110 '
b0100 (
b1000 )
b0100 *
0-
b0100 .
#33
0#
#34
1#
b0100 &
b1000 '
b0000 (
b0000 )
b0000 *
1-
b0001 .
#35
0#
#36
1#
b0001 &
b1110 '
b0100 (
b1000 )
b0100 *
0-
b0100 .
#37
0#
#38
1#
b0100 &
b1000 '
b0000 (
b0000 )
b0000 *
1-
b0001 .
#39
0#
#40
1#
b0001 &
b1110 '
b0100 (
b1000 )
b0100 *
0-
b0100 .
#41
0#
#42
1#
b0100 &
b1000 '
b0000 (
b0000 )
b0000 *
1-
b0001 .
#43
0#
#44
1#
b0001 &
b1110 '
b0100 (
b1000 )
b0100 *
0-
b0100 .
#45
0#
#46
1#
b0100 &
b1000 '
b0000 (
b0000 )
b0000 *
1-
b0001 .
#47
0#
#48
1#
b0001 &
b1110 '
b0100 (
b1000 )
b0100 *
0-
b0100 .
#49
0#
#50
1#
b0100 &
b1000 '
b0000 (
b0000 )
b0000 *
1-
b0001 .
#51
0#
#52
1#
b0001 &
b1110 '
b0100 (
b1000 )
b0100 *
0-
b0100 .
#53
0#
#54
1#
b0100 &
b1000 '
b0000 (
b0000 )
b0000 *
1-
b0001 .
#55
0#
#56
1#
b0001 &
b1110 '
b0100 (
b1000 )
b0100 *
0-
b0100 .
#57
0#
#58
1#
b0100 &
b1000 '
b0000 (
b0000 )
b0000 *
1-
b0001 .
#59
0#
#60
1#
b0001 &
b1110 '
b0100 (
b1000 )
b0100 *
0-
b0100 .
#61
0#
#62
1#
b0100 &
b1000 '
b0000 (
b0000 )
b0000 *
1-
b0001 .
#63
0#
#64
1#
b0001 &
b1110 '
b0100 (
b1000 )
b0100 *
0-
b0100 .
#65
0#
#66
1#
b0100 &
b1000 '
b0000 (
b0000 )
b0000 *
1-
b0001 .
#67
0#
#68
1#
b0001 &
b1110 '
b0100 (
b1000 )
b0100 *
0-
b0100 .
#69
0#
#70
1#
b0100 &
b1000 '
b0000 (
b0000 )
b0000 *
1-
b0001 .
#71
0#
#72
1#
b0001 &
b1110 '
b0100 (
b1000 )
b0100 *
0-
b0100 .
#73
0#
#74
1#
b0100 &
b1000 '
b0000 (
b0000 )
b0000 *
1-
b0001 .
#75
0#
#76
1#
b0001 &
b1110 '
b0100 (
b1000 )
b0100 *
0-
b0100 .
#77
0#
#78
1#
b0100 &
b1000 '
b0000 (
b0000 )
b0000 *
1-
b0001 .
#79
0#
#80
1#
b0001 &
b1110 '
b0100 (
b1000 )
b0100 *
0-
b0100 .
#81
0#
#82
1#
b0100 &
b1000 '
b0000 (
b0000 )
b0000 *
1-
b0001 .
#83
0#
#84
1#
b0001 &
b1110 '
b0100 (
b1000 )
b0100 *
0-
b0100 .
#85
0#
#86
1#
b0100 &
b1000 '
b0000 (
b0000 )
b0000 *
1-
b0001 .
#87
0#
#88
1#
b0001 &
b1110 '
b0100 (
b1000 )
b0100 *
0-
b0100 .
#89
0#
#90
1#
b0100 &
b1000 '
b0000 (
b0000 )
b0000 *
1-
b0001 .
#91
0#
#92
1#
b0001 &
b1110 '
b0100 (
b1000 )
b0100 *
0-
b0100 .
#93
0#
#94
1#
b0100 &
b1000 '
b0000 (
b0000 )
b0000 *
1-
b0001 .
#95
0#
#96
1#
b0001 &
b1110 '
b0100 (
b1000 )
b0100 *
0-
b0100 .
#97
0#
#98
1#
b0100 &
b1000 '
b0000 (
b0000 )
b0000 *
1-
b0001 .
#99
0#
#100
1#
b0001 &
b1110 '
b0100 (
b1000 )
b0100 *
0-
b0100 .
#101
0#
#102
1#
b0100 &
b1000 '
b0000 (
b0000 )
b0000 *
1-
b0001 .
#103
0#
#104
1#
b0001 &
b1110 '
b0100 (
b1000 )
b0100 *
0-
b0100 .
#105
0#
#106
1#
b0100 &
b1000 '
b0000 (
b0000 )
b0000 *
1-
b0001 .
#107
0#
#108
1#
b0001 &
b1110 '
b0100 (
b1000 )
b0100 *
0-
b0100 .
#109
0#
#110
1#
b0100 &
b1000 '
b0000 (
b0000 )
b0000 *
1-
b0001 .
#111
0#
#112
1#
b0001 &
b1110 '
b0100 (
b1000 )
b0100 *
0-
b0100 .
#113
0#
#114
1#
b0100 &
b1000 '
b0000 (
b0000 )
b0000 *
1-
b0001 .
#115
0#
#116
1#
b0001 &
b1110 '
b0100 (
b1000 )
b0100 *
0-
b0100 .
#117
0#
#118
1#
b0100 &
b1000 '
b0000 (
b0000 )
b0000 *
1-
b0001 .
#119
0#
#120
1#
b0001 &
b1110 '
b0100 (
b1000 )
b0100 *
0-
b0100 .
#121
0#
#122
1#
b0100 &
b1000 '
b0000 (
b0000 )
b0000 *
1-
b0001 .
#123
0#
#124
1#
b0001 &
b1110 '
b0100 (
b1000 )
b0100 *
0-
b0100 .
#125
0#
#126
1#
b0100 &
b1000 '
b0000 (
b0000 )
b0000 *
1-
b0001 .
#127
0#
#128
1#
b0001 &
b1110 '
b0100 (
b1000 )
b0100 *
0-
b0100 .
#129
0#
#130
1#
b0100 &
b1000 '
b0000 (
b0000 )
b0000 *
1-
b0001 .
#131
0#
#132
1#
b0001 &
b1110 '
b0100 (
b1000 )
b0100 *
0-
b0100 .
#133
0#
#134
1#
b0100 &
b1000 '
b0000 (
b0000 )
b0000 *
1-
b0001 .
#135
0#
#136
1#
b0001 &
b1110 '
b0100 (
b1000 )
b0100 *
0-
b0100 .
#137
0#
#138
1#
b0100 &
b1000 '
b0000 (
b0000 )
b0000 *
1-
b0001 .
#139
0#
#140
1#
b0001 &
b1110 '
b0100 (
b1000 )
b0100 *
0-
b0100 .
#141
0#
#142
1#
b0100 &
b1000 '
b0000 (
b0000 )
b0000 *
1-
b0001 .
#143
0#
#144
1#
b0001 &
b1110 '
b0100 (
b1000 )
b0100 *
0-
b0100 .
#145
0#
#146
1#
b0100 &
b1000 '
b0000 (
b0000 )
b0000 *
1-
b0001 .
#147
0#
#148
1#
b0001 &
b1110 '
b0100 (
b1000 )
b0100 *
0-
b0100 .
#149
0#
#150
1#
b0100 &
b1000 '
b0000 (
b0000 )
b0000 *
1-
b0001 .
#151
0#
#152
1#
b0001 &
b1110 '
b0100 (
b1000 )
b0100 *
0-
b0100 .
#153
0#
#154
1#
b0100 &
b1000 '
b0000 (
b0000 )
b0000 *
1-
b0001 .
#155
0#
#156
1#
b0001 &
b1110 '
b0100 (
b1000 )
b0100 *
0-
b0100 .
#157
0#
#158
1#
b0100 &
b1000 '
b0000 (
b0000 )
b0000 *
1-
b0001 .
#159
0#
#160
1#
b0001 &
b1110 '
b0100 (
b1000 )
b0100 *
0-
b0100 .
#161
0#
#162
1#
b0100 &
b1000 '
b0000 (
b0000 )
b0000 *
1-
b0001 .
#163
0#
#164
1#
b0001 &
b1110 '
b0100 (
b1000 )
b0100 *
0-
b0100 .
#165
0#
#166
1#
b0100 &
b1000 '
b0000 (
b0000 )
b0000 *
1-
b0001 .
#167
0#
#168
1#
b0001 &
b1110 '
b0100 (
b1000 )
b0100 *
0-
b0100 .
#169
0#
#170
1#
b0100 &
b1000 '
b0000 (
b0000 )
b0000 *
1-
b0001 .
#171
0#
#172
1#
b0001 &
b1110 '
b0100 (
b1000 )
b0100 *
0-
b0100 .
#173
0#
#174
1#
b0100 &
b1000 '
b0000 (
b0000 )
b0000 *
1-
b0001 .
#175
0#
#176
1#
b0001 &
b1110 '
b0100 (
b1000 )
b0100 *
0-
b0100 .
#177
0#
#178
1#
b0100 &
b1000 '
b0000 (
b0000 )
b0000 *
1-
b0001 .
#179
0#
#180
1#
b0001 &
b1110 '
b0100 (
b1000 )
b0100 *
0-
b0100 .
#181
0#
#182
1#
b0100 &
b1000 '
b0000 (
b0000 )
b0000 *
1-
b0001 .
#183
0#
#184
1#
b0001 &
b1110 '
b0100 (
b1000 )
b0100 *
0-
b0100 .
#185
0#
#186
1#
b0100 &
b1000 '
b0000 (
b0000 )
b0000 *
1-
b0001 .
#187
0#
#188
1#
b0001 &
b1110 '
b0100 (
b1000 )
b0100 *
0-
b0100 .
#189
0#
#190
1#
b0100 &
b1000 '
b0000 (
b0000 )
b0000 *
1-
b0001 .
#191
0#
#192
1#
b0001 &
b1110 '
b0100 (
b1000 )
b0100 *
0-
b0100 .
#193
0#
#194
1#
b0100 &
b1000 '
b0000 (
b0000 )
b0000 *
1-
b0001 .
#195
0#
#196
1#
b0001 &
b1110 '
b0100 (
b1000 )
b0100 *
0-
b0100 .
#197
0#
#198
1#
b0100 &
b1000 '
b0000 (
b0000 )
b0000 *
1-
b0001 .
#199
0#
#200
1#
b0001 &
b1110 '
b0100 (
b1000 )
b0100 *
0-
b0100 .
#201
0#
#202
1#
b0100 &
b1000 '
b0000 (
b0000 )
b0000 *
1-
b0001 .
#203
0#
#204
1#
b0001 &
b1110 '
b0100 (
b1000 )
b0100 *
0-
b0100 .
#205
0#
#206
1#
b0100 &
b1000 '
b0000 (
b0000 )
b0000 *
1-
b0001 .
#207
0#
#208
1#
b0001 &
b1110 '
b0100 (
b1000 )
b0100 *
0-
b0100 .
#209
0#
#210
1#
b0100 &
b1000 '
b0000 (
b0000 )
b0000 *
1-
b0001 .
#211
0#
#212
1#
b0001 &
b1110 '
b0100 (
b1000 )
b0100 *
0-
b0100 .
#213
0#
#214
1#
b0100 &
b1000 '
b0000 (
b0000 )
b0000 *
1-
b0001 .
#215
0#
#216
1#
b0001 &
b1110 '
b0100 (
b1000 )
b0100 *
0-
b0100 .
#217
0#
#218
1#
b0100 &
b1000 '
b0000 (
b0000 )
b0000 *
1-
b0001 .
#219
0#
#220
1#
b0001 &
b1110 '
b0100 (
b1000 )
b0100 *
0-
b0100 .
#221
0#
#222
1#
b0100 &
b1000 '
b0000 (
b0000 )
b0000 *
1-
b0001 .
#223
0#
#224
1#
b0001 &
b1110 '
b0100 (
b1000 )
b0100 *
0-
b0100 .
#225
0#
#226
1#
b0100 &
b1000 '
b0000 (
b0000 )
b0000 *
1-
b0001 .
#227
0#
#228
1#
b0001 &
b1110 '
b0100 (
b1000 )
b0100 *
0-
b0100 .
#229
0#
#230
1#
b0100 &
b1000 '
b0000 (
b0000 )
b0000 *
1-
b0001 .
#231
0#
#232
1#
b0001 &
b1110 '
b0100 (
b1000 )
b0100 *
0-
b0100 .
#233
0#
#234
1#
b0100 &
b1000 '
b0000 (
b0000 )
b0000 *
1-
b0001 .
#235
0#
#236
1#
b0001 &
b1110 '
b0100 (
b1000 )
b0100 *
0-
b0100 .
#237
0#
#238
1#
b0100 &
b1000 '
b0000 (
b0000 )
b0000 *
1-
b0001 .
#239
0#
#240
1#
b0001 &
b1110 '
b0100 (
b1000 )
b0100 *
0-
b0100 .
#241
0#
#242
1#
b0100 &
b1000 '
b0000 (
b0000 )
b0000 *
1-
b0001 .
#243
0#
#244
1#
b0001 &
b1110 '
b0100 (
b1000 )
b0100 *
0-
b0100 .
#245
0#
#246
1#
b0100 &
b1000 '
b0000 (
b0000 )
b0000 *
1-
b0001 .
#247
0#
#248
1#
b0001 &
b1110 '
b0100 (
b1000 )
b0100 *
0-
b0100 .
#249
0#
#250
1#
b0100 &
b1000 '
b0000 (
b0000 )
b0000 *
1-
b0001 .
#251
0#
#252
1#
b0001 &
b1110 '
b0100 (
b1000 )
b0100 *
0-
b0100 .
#253
0#
#254
1#
b0100 &
b1000 '
b0000 (
b0000 )
b0000 *
1-
b0001 .
#255
0#
#256
1#
b0001 &
b1110 '
b0100 (
b1000 )
b0100 *
0-
b0100 .
#257
0#
#258
1#
b0100 &
b1000 '
b0000 (
b0000 )
b0000 *
1-
b0001 .
#259
0#
#260
1#
b0001 &
b1110 '
b0100 (
b1000 )
b0100 *
0-
b0100 .
#261
0#
#262
1#
b0100 &
b1000 '
b0000 (
b0000 )
b0000 *
1-
b0001 .
#263
0#
#264
1#
b0001 &
b1110 '
b0100 (
b1000 )
b0100 *
0-
b0100 .
#265
0#
#266
1#
b0100 &
b1000 '
b0000 (
b0000 )
b0000 *
1-
b0001 .
#267
0#
#268
1#
b0001 &
b1110 '
b0100 (
b1000 )
b0100 *
0-
b0100 .
#269
0#
#270
1#
b0100 &
b1000 '
b0000 (
b0000 )
b0000 *
1-
b0001 .
#271
0#
#272
1#
b0001 &
b1110 '
b0100 (
b1000 )
b0100 *
0-
b0100 .
#273
0#
#274
1#
b0100 &
b1000 '
b0000 (
b0000 )
b0000 *
1-
b0001 .
#275
0#
#276
1#
b0001 &
b1110 '
b0100 (
b1000 )
b0100 *
0-
b0100 .
#277
0#
#278
1#
b0100 &
b1000 '
b0000 (
b0000 )
b0000 *
1-
b0001 .
#279
0#
#280
1#
b0001 &
b1110 '
b0100 (
b1000 )
b0100 *
0-
b0100 .
#281
0#
#282
1#
b0100 &
b1000 '
b0000 (
b0000 )
b0000 *
1-
b0001 .
#283
0#
#284
1#
b0001 &
b1110 '
b0100 (
b1000 )
b0100 *
0-
b0100 .
#285
0#
#286
1#
b0100 &
b1000 '
b0000 (
b0000 )
b0000 *
1-
b0001 .
#287
0#
#288
1#
b0001 &
b1110 '
b0100 (
b1000 )
b0100 *
0-
b0100 .
#289
0#
#290
1#
b0100 &
b1000 '
b0000 (
b0000 )
b0000 *
1-
b0001 .
#291
0#
#292
1#
b0001 &
b1110 '
b0100 (
b1000 )
b0100 *
0-
b0100 .
#293
0#
#294
1#
b0100 &
b1000 '
b0000 (
b0000 )
b0000 *
1-
b0001 .
#295
0#
#296
1#
b0001 &
b1110 '
b0100 (
b1000 )
b0100 *
0-
b0100 .
#297
0#
#298
1#
b0100 &
b1000 '
b0000 (
b0000 )
b0000 *
1-
b0001 .
