counter/Counter.v
module Counter(
    input       clk,
    input       rst_n,
    input       cntEn,
    output  [63:0]  cnt
);

reg     [15:0]      cnt1;
reg     [15:0]      cnt2;
reg     [15:0]      cnt3;
reg     [15:0]      cnt4;

always @(posedge clk or negedge rst_n) begin
    if(!rst_n)
        cnt1 <= 'd0;
    else if(cntEn)
        cnt1 <= cnt1 + 1'b1;
    else
        cnt1 <= cnt1;
end

always @(posedge clk or negedge rst_n) begin
    if(!rst_n)
        cnt2 <= 'd0;
    else if(&cnt1)
        cnt2 <= cnt2 + 1'b1;
    else
        cnt2 <= cnt2;
end

always @(posedge clk or negedge rst_n) begin
    if(!rst_n)
        cnt3 <= 'd0;
    else if(&cnt2)
        cnt3 <= cnt3 + 1'b1;
    else
        cnt3 <= cnt3;
end

always @(posedge clk or negedge rst_n) begin
    if(!rst_n)
        cnt4 <= 'd0;
    else if(&cnt3)
        cnt4 <= cnt4 + 1'b1;
    else
        cnt4 <= cnt4;
end

assign cnt = {cnt4,cnt3,cnt2,cnt1};

endmodule

counter/waveform.vcd
$version Generated by VerilatedVcd $end
$timescale 1ps $end

 $scope module TOP $end
  $var wire  1 ' clk $end
  $var wire 64 * cnt [63:0] $end
  $var wire  1 ) cntEn $end
  $var wire  1 ( rst_n $end
  $scope module Counter $end
   $var wire  1 ' clk $end
   $var wire 64 * cnt [63:0] $end
   $var wire 16 # cnt1 [15:0] $end
   $var wire 16 $ cnt2 [15:0] $end
   $var wire 16 % cnt3 [15:0] $end
   $var wire 16 & cnt4 [15:0] $end
   $var wire  1 ) cntEn $end
   $var wire  1 ( rst_n $end
  $upscope $end
 $upscope $end
$enddefinitions $end


#0
b0000000000000000 #
b0000000000000000 $
b0000000000000000 %
b0000000000000000 &
1'
1(
0)
b0000000000000000000000000000000000000000000000000000000000000000 *
#1
0'
0(
#2
1'
#3
0'
#4
1'
#5
0'
#6
1'
1(
#7
0'
#8
1'
#9
0'
#10
1'
1)
#11
0'
#12
b0000000000000001 #
1'
b0000000000000000000000000000000000000000000000000000000000000001 *
#13
0'
#14
b0000000000000010 #
1'
b0000000000000000000000000000000000000000000000000000000000000010 *
#15
0'
#16
b0000000000000011 #
1'
b0000000000000000000000000000000000000000000000000000000000000011 *
#17
0'
#18
b0000000000000100 #
1'
b0000000000000000000000000000000000000000000000000000000000000100 *
#19
0'
#20
b0000000000000101 #
1'
0)
b0000000000000000000000000000000000000000000000000000000000000101 *
#21
0'
#22
1'
#23
0'
#24
1'
#25
0'
#26
1'
#27
0'
#28
1'
#29
0'
#30
1'
1)
#31
0'
#32
b0000000000000110 #
1'
b0000000000000000000000000000000000000000000000000000000000000110 *
#33
0'
#34
b0000000000000111 #
1'
b0000000000000000000000000000000000000000000000000000000000000111 *
#35
0'
#36
b0000000000001000 #
1'
b0000000000000000000000000000000000000000000000000000000000001000 *
#37
0'
#38
b0000000000001001 #
1'
b0000000000000000000000000000000000000000000000000000000000001001 *
#39
0'
#40
b0000000000001010 #
1'
b0000000000000000000000000000000000000000000000000000000000001010 *
#41
0'
#42
b0000000000001011 #
1'
b0000000000000000000000000000000000000000000000000000000000001011 *
#43
0'
#44
b0000000000001100 #
1'
b0000000000000000000000000000000000000000000000000000000000001100 *
#45
0'
#46
b0000000000001101 #
1'
b0000000000000000000000000000000000000000000000000000000000001101 *
#47
0'
#48
b0000000000001110 #
1'
b0000000000000000000000000000000000000000000000000000000000001110 *
#49
0'
#50
b0000000000001111 #
1'
b0000000000000000000000000000000000000000000000000000000000001111 *
#51
0'
#52
b0000000000010000 #
1'
b0000000000000000000000000000000000000000000000000000000000010000 *
#53
0'
#54
b0000000000010001 #
1'
b0000000000000000000000000000000000000000000000000000000000010001 *
#55
0'
#56
b0000000000010010 #
1'
b0000000000000000000000000000000000000000000000000000000000010010 *
#57
0'
#58
b0000000000010011 #
1'
b0000000000000000000000000000000000000000000000000000000000010011 *
#59
0'
#60
b0000000000010100 #
1'
b0000000000000000000000000000000000000000000000000000000000010100 *
#61
0'
#62
b0000000000010101 #
1'
b0000000000000000000000000000000000000000000000000000000000010101 *
#63
0'
#64
b0000000000010110 #
1'
b0000000000000000000000000000000000000000000000000000000000010110 *
#65
0'
#66
b0000000000010111 #
1'
b0000000000000000000000000000000000000000000000000000000000010111 *
#67
0'
#68
b0000000000011000 #
1'
b0000000000000000000000000000000000000000000000000000000000011000 *
#69
0'
#70
b0000000000011001 #
1'
b0000000000000000000000000000000000000000000000000000000000011001 *
#71
0'
#72
b0000000000011010 #
1'
b0000000000000000000000000000000000000000000000000000000000011010 *
#73
0'
#74
b0000000000011011 #
1'
b0000000000000000000000000000000000000000000000000000000000011011 *
#75
0'
#76
b0000000000011100 #
1'
b0000000000000000000000000000000000000000000000000000000000011100 *
#77
0'
#78
b0000000000011101 #
1'
b0000000000000000000000000000000000000000000000000000000000011101 *
#79
0'
#80
b0000000000011110 #
1'
b0000000000000000000000000000000000000000000000000000000000011110 *
#81
0'
#82
b0000000000011111 #
1'
b0000000000000000000000000000000000000000000000000000000000011111 *
#83
0'
#84
b0000000000100000 #
1'
b0000000000000000000000000000000000000000000000000000000000100000 *
#85
0'
#86
b0000000000100001 #
1'
b0000000000000000000000000000000000000000000000000000000000100001 *
#87
0'
#88
b0000000000100010 #
1'
b0000000000000000000000000000000000000000000000000000000000100010 *
#89
0'
#90
b0000000000100011 #
1'
b0000000000000000000000000000000000000000000000000000000000100011 *
#91
0'
#92
b0000000000100100 #
1'
b0000000000000000000000000000000000000000000000000000000000100100 *
#93
0'
#94
b0000000000100101 #
1'
b0000000000000000000000000000000000000000000000000000000000100101 *
#95
0'
#96
b0000000000100110 #
1'
b0000000000000000000000000000000000000000000000000000000000100110 *
#97
0'
#98
b0000000000100111 #
1'
b0000000000000000000000000000000000000000000000000000000000100111 *
#99
0'
#100
b0000000000101000 #
1'
b0000000000000000000000000000000000000000000000000000000000101000 *
#101
0'
#102
b0000000000101001 #
1'
b0000000000000000000000000000000000000000000000000000000000101001 *
#103
0'
#104
b0000000000101010 #
1'
b0000000000000000000000000000000000000000000000000000000000101010 *
#105
0'
#106
b0000000000101011 #
1'
b0000000000000000000000000000000000000000000000000000000000101011 *
#107
0'
#108
b0000000000101100 #
1'
b0000000000000000000000000000000000000000000000000000000000101100 *
#109
0'
#110
b0000000000101101 #
1'
b0000000000000000000000000000000000000000000000000000000000101101 *
#111
0'
#112
b0000000000101110 #
1'
b0000000000000000000000000000000000000000000000000000000000101110 *
#113
0'
#114
b0000000000101111 #
1'
b0000000000000000000000000000000000000000000000000000000000101111 *
#115
0'
#116
b0000000000110000 #
1'
b0000000000000000000000000000000000000000000000000000000000110000 *
#117
0'
#118
b0000000000110001 #
1'
b0000000000000000000000000000000000000000000000000000000000110001 *
#119
0'
#120
b0000000000110010 #
1'
b0000000000000000000000000000000000000000000000000000000000110010 *
#121
0'
#122
b0000000000110011 #
1'
b0000000000000000000000000000000000000000000000000000000000110011 *
#123
0'
#124
b0000000000110100 #
1'
b0000000000000000000000000000000000000000000000000000000000110100 *
#125
0'
#126
b0000000000110101 #
1'
b0000000000000000000000000000000000000000000000000000000000110101 *
#127
0'
#128
b0000000000110110 #
1'
b0000000000000000000000000000000000000000000000000000000000110110 *
#129
0'
#130
b0000000000110111 #
1'
b0000000000000000000000000000000000000000000000000000000000110111 *
#131
0'
#132
b0000000000111000 #
1'
b0000000000000000000000000000000000000000000000000000000000111000 *
#133
0'
#134
b0000000000111001 #
1'
b0000000000000000000000000000000000000000000000000000000000111001 *
#135
0'
#136
b0000000000111010 #
1'
b0000000000000000000000000000000000000000000000000000000000111010 *
#137
0'
#138
b0000000000111011 #
1'
b0000000000000000000000000000000000000000000000000000000000111011 *
#139
0'
#140
b0000000000111100 #
1'
b0000000000000000000000000000000000000000000000000000000000111100 *
#141
0'
#142
b0000000000111101 #
1'
b0000000000000000000000000000000000000000000000000000000000111101 *
#143
0'
#144
b0000000000111110 #
1'
b0000000000000000000000000000000000000000000000000000000000111110 *
#145
0'
#146
b0000000000111111 #
1'
b0000000000000000000000000000000000000000000000000000000000111111 *
#147
0'
#148
b0000000001000000 #
1'
b0000000000000000000000000000000000000000000000000000000001000000 *
#149
0'
#150
b0000000001000001 #
1'
b0000000000000000000000000000000000000000000000000000000001000001 *
#151
0'
#152
b0000000001000010 #
1'
b0000000000000000000000000000000000000000000000000000000001000010 *
#153
0'
#154
b0000000001000011 #
1'
b0000000000000000000000000000000000000000000000000000000001000011 *
#155
0'
#156
b0000000001000100 #
1'
b0000000000000000000000000000000000000000000000000000000001000100 *
#157
0'
#158
b0000000001000101 #
1'
b0000000000000000000000000000000000000000000000000000000001000101 *
#159
0'
#160
b0000000001000110 #
1'
b0000000000000000000000000000000000000000000000000000000001000110 *
#161
0'
#162
b0000000001000111 #
1'
b0000000000000000000000000000000000000000000000000000000001000111 *
#163
0'
#164
b0000000001001000 #
1'
b0000000000000000000000000000000000000000000000000000000001001000 *
#165
0'
#166
b0000000001001001 #
1'
b0000000000000000000000000000000000000000000000000000000001001001 *
#167
0'
#168
b0000000001001010 #
1'
b0000000000000000000000000000000000000000000000000000000001001010 *
#169
0'
#170
b0000000001001011 #
1'
b0000000000000000000000000000000000000000000000000000000001001011 *
#171
0'
#172
b0000000001001100 #
1'
b0000000000000000000000000000000000000000000000000000000001001100 *
#173
0'
#174
b0000000001001101 #
1'
b0000000000000000000000000000000000000000000000000000000001001101 *
#175
0'
#176
b0000000001001110 #
1'
b0000000000000000000000000000000000000000000000000000000001001110 *
#177
0'
#178
b0000000001001111 #
1'
b0000000000000000000000000000000000000000000000000000000001001111 *
#179
0'
#180
b0000000001010000 #
1'
b0000000000000000000000000000000000000000000000000000000001010000 *
#181
0'
#182
b0000000001010001 #
1'
b0000000000000000000000000000000000000000000000000000000001010001 *
#183
0'
#184
b0000000001010010 #
1'
b0000000000000000000000000000000000000000000000000000000001010010 *
#185
0'
#186
b0000000001010011 #
1'
b0000000000000000000000000000000000000000000000000000000001010011 *
#187
0'
#188
b0000000001010100 #
1'
b0000000000000000000000000000000000000000000000000000000001010100 *
#189
0'
#190
b0000000001010101 #
1'
b0000000000000000000000000000000000000000000000000000000001010101 *
#191
0'
#192
b0000000001010110 #
1'
b0000000000000000000000000000000000000000000000000000000001010110 *
#193
0'
#194
b0000000001010111 #
1'
b0000000000000000000000000000000000000000000000000000000001010111 *
#195
0'
#196
b0000000001011000 #
1'
b0000000000000000000000000000000000000000000000000000000001011000 *
#197
0'
#198
b0000000001011001 #
1'
b0000000000000000000000000000000000000000000000000000000001011001 *
#199
0'
#200
b0000000001011010 #
1'
b0000000000000000000000000000000000000000000000000000000001011010 *
#201
0'
#202
b0000000001011011 #
1'
b0000000000000000000000000000000000000000000000000000000001011011 *
#203
0'
#204
b0000000001011100 #
1'
b0000000000000000000000000000000000000000000000000000000001011100 *
#205
0'
#206
b0000000001011101 #
1'
b0000000000000000000000000000000000000000000000000000000001011101 *
#207
0'
#208
b0000000001011110 #
1'
b0000000000000000000000000000000000000000000000000000000001011110 *
#209
0'
#210
b0000000001011111 #
1'
b0000000000000000000000000000000000000000000000000000000001011111 *
#211
0'
#212
b0000000001100000 #
1'
b0000000000000000000000000000000000000000000000000000000001100000 *
#213
0'
#214
b0000000001100001 #
1'
b0000000000000000000000000000000000000000000000000000000001100001 *
#215
0'
#216
b0000000001100010 #
1'
b0000000000000000000000000000000000000000000000000000000001100010 *
#217
0'
#218
b0000000001100011 #
1'
b0000000000000000000000000000000000000000000000000000000001100011 *
#219
0'
#220
b0000000001100100 #
1'
b0000000000000000000000000000000000000000000000000000000001100100 *
#221
0'
#222
b0000000001100101 #
1'
b0000000000000000000000000000000000000000000000000000000001100101 *
#223
0'
#224
b0000000001100110 #
1'
b0000000000000000000000000000000000000000000000000000000001100110 *
#225
0'
#226
b0000000001100111 #
1'
b0000000000000000000000000000000000000000000000000000000001100111 *
#227
0'
#228
b0000000001101000 #
1'
b0000000000000000000000000000000000000000000000000000000001101000 *
#229
0'
#230
b0000000001101001 #
1'
b0000000000000000000000000000000000000000000000000000000001101001 *
#231
0'
#232
b0000000001101010 #
1'
b0000000000000000000000000000000000000000000000000000000001101010 *
#233
0'
#234
b0000000001101011 #
1'
b0000000000000000000000000000000000000000000000000000000001101011 *
#235
0'
#236
b0000000001101100 #
1'
b0000000000000000000000000000000000000000000000000000000001101100 *
#237
0'
#238
b0000000001101101 #
1'
b0000000000000000000000000000000000000000000000000000000001101101 *
#239
0'
#240
b0000000001101110 #
1'
b0000000000000000000000000000000000000000000000000000000001101110 *
#241
0'
#242
b0000000001101111 #
1'
b0000000000000000000000000000000000000000000000000000000001101111 *
#243
0'
#244
b0000000001110000 #
1'
b0000000000000000000000000000000000000000000000000000000001110000 *
#245
0'
#246
b0000000001110001 #
1'
b0000000000000000000000000000000000000000000000000000000001110001 *
#247
0'
#248
b0000000001110010 #
1'
b0000000000000000000000000000000000000000000000000000000001110010 *
#249
0'
#250
b0000000001110011 #
1'
b0000000000000000000000000000000000000000000000000000000001110011 *
#251
0'
#252
b0000000001110100 #
1'
b0000000000000000000000000000000000000000000000000000000001110100 *
#253
0'
#254
b0000000001110101 #
1'
b0000000000000000000000000000000000000000000000000000000001110101 *
#255
0'
#256
b0000000001110110 #
1'
b0000000000000000000000000000000000000000000000000000000001110110 *
#257
0'
#258
b0000000001110111 #
1'
b0000000000000000000000000000000000000000000000000000000001110111 *
#259
0'
#260
b0000000001111000 #
1'
b0000000000000000000000000000000000000000000000000000000001111000 *
#261
0'
#262
b0000000001111001 #
1'
b0000000000000000000000000000000000000000000000000000000001111001 *
#263
0'
#264
b0000000001111010 #
1'
b0000000000000000000000000000000000000000000000000000000001111010 *
#265
0'
#266
b0000000001111011 #
1'
b0000000000000000000000000000000000000000000000000000000001111011 *
#267
0'
#268
b0000000001111100 #
1'
b0000000000000000000000000000000000000000000000000000000001111100 *
#269
0'
#270
b0000000001111101 #
1'
b0000000000000000000000000000000000000000000000000000000001111101 *
#271
0'
#272
b0000000001111110 #
1'
b0000000000000000000000000000000000000000000000000000000001111110 *
#273
0'
#274
b0000000001111111 #
1'
b0000000000000000000000000000000000000000000000000000000001111111 *
#275
0'
#276
b0000000010000000 #
1'
b0000000000000000000000000000000000000000000000000000000010000000 *
#277
0'
#278
b0000000010000001 #
1'
b0000000000000000000000000000000000000000000000000000000010000001 *
#279
0'
#280
b0000000010000010 #
1'
b0000000000000000000000000000000000000000000000000000000010000010 *
#281
0'
#282
b0000000010000011 #
1'
b0000000000000000000000000000000000000000000000000000000010000011 *
#283
0'
#284
b0000000010000100 #
1'
b0000000000000000000000000000000000000000000000000000000010000100 *
#285
0'
#286
b0000000010000101 #
1'
b0000000000000000000000000000000000000000000000000000000010000101 *
#287
0'
#288
b0000000010000110 #
1'
b0000000000000000000000000000000000000000000000000000000010000110 *
#289
0'
#290
b0000000010000111 #
1'
b0000000000000000000000000000000000000000000000000000000010000111 *
#291
0'
#292
b0000000010001000 #
1'
b0000000000000000000000000000000000000000000000000000000010001000 *
#293
0'
#294
b0000000010001001 #
1'
b0000000000000000000000000000000000000000000000000000000010001001 *
#295
0'
#296
b0000000010001010 #
1'
b0000000000000000000000000000000000000000000000000000000010001010 *
#297
0'
#298
b0000000010001011 #
1'
b0000000000000000000000000000000000000000000000000000000010001011 *
