clk_switch/clk_sw_ff.v
`timescale 1ns/1ps
// 时钟切换模块
module clk_sw_ff(
    input           clka,
    input           clkb,
    input           rst_n,
    input           sel,
    output          clk_out
);

reg     clka_out;
always @(posedge clka or negedge rst_n) begin
    if(!rst_n)
        clka_out <= 1'b0;
    else
        clka_out <= (~clkb_out_r) & sel; // sel为1时，选择输出clka
end
reg     clka_out_r;
always @(negedge clka or negedge rst_n) begin
    if(!rst_n)
        clka_out_r <= 1'b0;
    else
        clka_out_r <= clka_out;
end

reg     clkb_out;
always @(posedge clkb or negedge rst_n) begin
    if(!rst_n)
        clkb_out <= 1'b0;
    else
        clkb_out <= (~clka_out_r) & (~sel); // sel为0时，选择输出clkb
end
reg     clkb_out_r;
always @(negedge clkb or negedge rst_n) begin
    if(!rst_n)
        clkb_out_r <= 1'b0;
    else
        clkb_out_r <= clkb_out;
end

assign clk_out = (clka & clka_out_r) | (clkb & clkb_out_r);

endmodule

clk_switch/waveform.vcd
$version Generated by VerilatedVcd $end
$timescale 1ps $end

 $scope module TOP $end
  $var wire  1 ' clk_out $end
  $var wire  1 # clka $end
  $var wire  1 $ clkb $end
  $var wire  1 % rst_n $end
  $var wire  1 & sel $end
  $scope module clk_sw_ff $end
   $var wire  1 ' clk_out $end
   $var wire  1 # clka $end
   $var wire  1 ( clka_out $end
   $var wire  1 ) clka_out_r $end
   $var wire  1 $ clkb $end
   $var wire  1 * clkb_out $end
   $var wire  1 + clkb_out_r $end
   $var wire  1 % rst_n $end
   $var wire  1 & sel $end
  $upscope $end
 $upscope $end
$enddefinitions $end


#0
1#
1$
1%
0&
0'
0(
0)
0*
0+
#1
0#
0%
#2
1#
0$
#3
0#
#4
1#
1$
#5
0#
#6
1#
0$
1%
#7
0#
#8
1#
1$
1*
#9
0#
#10
1#
0$
1&
1+
#11
0#
#12
1#
1$
1'
0*
#13
0#
#14
1#
0$
0'
0+
#15
0#
#16
1#
1$
1(
#17
0#
1)
#18
1#
0$
1'
#19
0#
0'
#20
1#
1$
1'
#21
0#
0'
#22
1#
0$
1'
#23
0#
0'
#24
1#
1$
1'
#25
0#
0'
#26
1#
0$
1'
#27
0#
0'
#28
1#
1$
1'
#29
0#
0'
#30
1#
0$
1'
#31
0#
0'
#32
1#
1$
1'
#33
0#
0'
#34
1#
0$
1'
#35
0#
0'
#36
1#
1$
1'
#37
0#
0'
#38
1#
0$
1'
#39
0#
0'
#40
1#
1$
1'
#41
0#
0'
#42
1#
0$
1'
#43
0#
0'
#44
1#
1$
1'
#45
0#
0'
#46
1#
0$
1'
#47
0#
0'
#48
1#
1$
1'
#49
0#
0'
#50
1#
0$
1'
#51
0#
0'
#52
1#
1$
0&
1'
#53
0#
0'
#54
1#
0$
1'
0(
#55
0#
0'
0)
#56
1#
1$
1*
#57
0#
#58
1#
0$
1+
#59
0#
#60
1#
1$
1'
#61
0#
#62
1#
0$
0'
#63
0#
#64
1#
1$
1'
#65
0#
#66
1#
0$
0'
#67
0#
#68
1#
1$
1'
#69
0#
#70
1#
0$
0'
#71
0#
#72
1#
1$
1'
#73
0#
#74
1#
0$
0'
#75
0#
#76
1#
1$
1'
#77
0#
#78
1#
0$
0'
#79
0#
#80
1#
1$
1'
#81
0#
#82
1#
0$
0'
#83
0#
#84
1#
1$
1'
#85
0#
#86
1#
0$
0'
#87
0#
#88
1#
1$
1'
#89
0#
#90
1#
0$
0'
#91
0#
#92
1#
1$
1'
#93
0#
#94
1#
0$
0'
#95
0#
#96
1#
1$
1'
#97
0#
#98
1#
0$
1&
0'
#99
0#
#100
1#
1$
1'
0*
#101
0#
#102
1#
0$
0'
0+
#103
0#
#104
1#
1$
1(
#105
0#
1)
#106
1#
0$
1'
#107
0#
0'
#108
1#
1$
1'
#109
0#
0'
#110
1#
0$
1'
#111
0#
0'
#112
1#
1$
1'
#113
0#
0'
#114
1#
0$
1'
#115
0#
0'
#116
1#
1$
1'
#117
0#
0'
#118
1#
0$
1'
#119
0#
0'
#120
1#
1$
1'
#121
0#
0'
#122
1#
0$
1'
#123
0#
0'
#124
1#
1$
1'
#125
0#
0'
#126
1#
0$
1'
#127
0#
0'
#128
1#
1$
1'
#129
0#
0'
#130
1#
0$
1'
#131
0#
0'
#132
1#
1$
1'
#133
0#
0'
#134
1#
0$
1'
#135
0#
0'
#136
1#
1$
1'
#137
0#
0'
#138
1#
0$
1'
#139
0#
0'
#140
1#
1$
1'
#141
0#
0'
#142
1#
0$
1'
#143
0#
0'
#144
1#
1$
1'
#145
0#
0'
#146
1#
0$
1'
#147
0#
0'
#148
1#
1$
1'
#149
0#
0'
#150
1#
0$
1'
#151
0#
0'
#152
1#
1$
1'
#153
0#
0'
#154
1#
0$
1'
#155
0#
0'
#156
1#
1$
1'
#157
0#
0'
#158
1#
0$
1'
#159
0#
0'
#160
1#
1$
1'
#161
0#
0'
#162
1#
0$
1'
#163
0#
0'
#164
1#
1$
1'
#165
0#
0'
#166
1#
0$
1'
#167
0#
0'
#168
1#
1$
1'
#169
0#
0'
#170
1#
0$
1'
#171
0#
0'
#172
1#
1$
1'
#173
0#
0'
#174
1#
0$
1'
#175
0#
0'
#176
1#
1$
0&
1'
#177
0#
0'
#178
1#
0$
1'
0(
#179
0#
0'
0)
#180
1#
1$
1*
#181
0#
#182
1#
0$
1+
#183
0#
#184
1#
1$
1'
#185
0#
#186
1#
0$
0'
#187
0#
#188
1#
1$
1'
#189
0#
#190
1#
0$
0'
#191
0#
#192
1#
1$
1'
#193
0#
#194
1#
0$
0'
#195
0#
#196
1#
1$
1'
#197
0#
#198
1#
0$
0'
#199
0#
#200
1#
1$
1'
#201
0#
#202
1#
0$
0'
#203
0#
#204
1#
1$
1'
#205
0#
#206
1#
0$
0'
#207
0#
#208
1#
1$
1'
#209
0#
#210
1#
0$
0'
#211
0#
#212
1#
1$
1'
#213
0#
#214
1#
0$
0'
#215
0#
#216
1#
1$
1'
#217
0#
#218
1#
0$
0'
#219
0#
#220
1#
1$
1'
#221
0#
#222
1#
0$
0'
#223
0#
#224
1#
1$
1'
#225
0#
#226
1#
0$
0'
#227
0#
#228
1#
1$
1'
#229
0#
#230
1#
0$
0'
#231
0#
#232
1#
1$
1'
#233
0#
#234
1#
0$
0'
#235
0#
#236
1#
1$
1'
#237
0#
#238
1#
0$
0'
#239
0#
#240
1#
1$
1'
#241
0#
#242
1#
0$
0'
#243
0#
#244
1#
1$
1'
#245
0#
#246
1#
0$
0'
#247
0#
#248
1#
1$
1'
#249
0#
#250
1#
0$
0'
#251
0#
#252
1#
1$
1'
#253
0#
#254
1#
0$
0'
#255
0#
#256
1#
1$
1'
#257
0#
1&
