uart/uart_tx.v
`timescale 1ns/1ns

module uart_tx#(parameter
    CLK     =   'd100_000_100,
    BPS     =   'd9600
)(
    input               clk ,
    input               rst_n,
    input   [7:0]       pi_data,
    input               pi_flag,
    output  reg         tx
);

/* verilator lint_off WIDTHEXPAND */

localparam BAUD_CNT_MAX = CLK / BPS;
localparam BAUD_CNT_WIDTH = $clog2(BAUD_CNT_MAX);

reg     [7:0]   tx_data;
always @(posedge clk or negedge rst_n) begin
    if(!rst_n)
        tx_data <= 'd0;
    else if(pi_flag)
        tx_data <= pi_data;
    else
        tx_data <= tx_data;
end

reg     work_en /*verilator public_flat_rw*/; 
always @(posedge clk or negedge rst_n) begin
    if(!rst_n)
        work_en <= 1'b0;
    else if(pi_flag)
        work_en <= 1'b1;
    else if(bit_cnt == 'd9 && bit_flag)
        work_en <= 1'b0;
end

reg     [BAUD_CNT_WIDTH:0]  baud_cnt;
always @(posedge clk or negedge rst_n) begin
    if(!rst_n)
        baud_cnt <= 'd0;
    else if(baud_cnt == BAUD_CNT_MAX-1 && work_en)
        baud_cnt <= 'd0;
    else if(work_en)
        baud_cnt <= baud_cnt + 1'b1;
    else
        baud_cnt <= 'd0;
end

reg     bit_flag;
always @(posedge clk or negedge rst_n) begin
    if(!rst_n)
        bit_flag <= 1'b0;
    else if(baud_cnt == 'd1)
        bit_flag <= 1'b1;
    else
        bit_flag <= 1'b0;
end

reg     [3:0]   bit_cnt;
always @(posedge clk or negedge rst_n) begin
    if(!rst_n)
        bit_cnt <= 'd0;
    else if(bit_flag && bit_cnt == 'd9)
        bit_cnt <= 'd0;
    else if(bit_flag)
        bit_cnt <= bit_cnt + 1'b1;
    else
        bit_cnt <= bit_cnt;
end

always @(posedge clk or negedge rst_n) begin
    if(!rst_n)
        tx <= 1'b1;
    else if(bit_flag)
        case(bit_cnt)
            0 : tx <= 1'b0;
            1 : tx <= tx_data[0];
            2 : tx <= tx_data[1];
            3 : tx <= tx_data[2];
            4 : tx <= tx_data[3];
            5 : tx <= tx_data[4];
            6 : tx <= tx_data[5];
            7 : tx <= tx_data[6];
            8 : tx <= tx_data[7];
            9 : tx <= 1'b1;
            default : tx <= 1'b1;
        endcase
end

endmodule

uart/waveform.vcd
$version Generated by VerilatedVcd $end
$timescale 1ns $end

 $scope module TOP $end
  $var wire  1 ( clk $end
  $var wire  8 * pi_data [7:0] $end
  $var wire  1 + pi_flag $end
  $var wire  1 ) rst_n $end
  $var wire  1 , tx $end
  $scope module uart_tx $end
   $var wire 32 / BAUD_CNT_MAX [31:0] $end
   $var wire 32 0 BAUD_CNT_WIDTH [31:0] $end
   $var wire 32 . BPS [31:0] $end
   $var wire 32 - CLK [31:0] $end
   $var wire  6 % baud_cnt [5:0] $end
   $var wire  4 ' bit_cnt [3:0] $end
   $var wire  1 & bit_flag $end
   $var wire  1 ( clk $end
   $var wire  8 * pi_data [7:0] $end
   $var wire  1 + pi_flag $end
   $var wire  1 ) rst_n $end
   $var wire  1 , tx $end
   $var wire  8 # tx_data [7:0] $end
   $var wire  1 $ work_en $end
  $upscope $end
 $upscope $end
$enddefinitions $end


#0
b00000000 #
0$
b000000 %
0&
b0000 '
1(
1)
b00000000 *
0+
0,
b00000000000000011000011010100000 -
b00000000000000000001001110001000 .
b00000000000000000000000000010100 /
b00000000000000000000000000000101 0
#1
0(
#2
1(
0)
1,
#3
0(
#4
1(
#5
0(
#6
1(
1)
#7
0(
#8
1(
b11100111 *
1+
#9
0(
#10
b11100111 #
1$
1(
0+
#11
0(
#12
b000001 %
1(
#13
0(
#14
b000010 %
1&
1(
#15
0(
#16
b000011 %
0&
b0001 '
1(
0,
#17
0(
#18
b000100 %
1(
#19
0(
#20
b000101 %
1(
#21
0(
#22
b000110 %
1(
#23
0(
#24
b000111 %
1(
#25
0(
#26
b001000 %
1(
#27
0(
#28
b001001 %
1(
#29
0(
#30
b001010 %
1(
#31
0(
#32
b001011 %
1(
#33
0(
#34
b001100 %
1(
#35
0(
#36
b001101 %
1(
#37
0(
#38
b001110 %
1(
#39
0(
#40
b001111 %
1(
#41
0(
#42
b010000 %
1(
#43
0(
#44
b010001 %
1(
#45
0(
#46
b010010 %
1(
#47
0(
#48
b010011 %
1(
#49
0(
#50
b000000 %
1(
#51
0(
#52
b000001 %
1(
#53
0(
#54
b000010 %
1&
1(
#55
0(
#56
b000011 %
0&
b0010 '
1(
1,
#57
0(
#58
b000100 %
1(
#59
0(
#60
b000101 %
1(
#61
0(
#62
b000110 %
1(
#63
0(
#64
b000111 %
1(
#65
0(
#66
b001000 %
1(
#67
0(
#68
b001001 %
1(
#69
0(
#70
b001010 %
1(
#71
0(
#72
b001011 %
1(
#73
0(
#74
b001100 %
1(
#75
0(
#76
b001101 %
1(
#77
0(
#78
b001110 %
1(
#79
0(
#80
b001111 %
1(
#81
0(
#82
b010000 %
1(
#83
0(
#84
b010001 %
1(
#85
0(
#86
b010010 %
1(
#87
0(
#88
b010011 %
1(
#89
0(
#90
b000000 %
1(
#91
0(
#92
b000001 %
1(
#93
0(
#94
b000010 %
1&
1(
#95
0(
#96
b000011 %
0&
b0011 '
1(
#97
0(
#98
b000100 %
1(
#99
0(
#100
b000101 %
1(
#101
0(
#102
b000110 %
1(
#103
0(
#104
b000111 %
1(
#105
0(
#106
b001000 %
1(
#107
0(
#108
b001001 %
1(
#109
0(
#110
b001010 %
1(
#111
0(
#112
b001011 %
1(
#113
0(
#114
b001100 %
1(
#115
0(
#116
b001101 %
1(
#117
0(
#118
b001110 %
1(
#119
0(
#120
b001111 %
1(
#121
0(
#122
b010000 %
1(
#123
0(
#124
b010001 %
1(
#125
0(
#126
b010010 %
1(
#127
0(
#128
b010011 %
1(
#129
0(
#130
b000000 %
1(
#131
0(
#132
b000001 %
1(
#133
0(
#134
b000010 %
1&
1(
#135
0(
#136
b000011 %
0&
b0100 '
1(
#137
0(
#138
b000100 %
1(
#139
0(
#140
b000101 %
1(
#141
0(
#142
b000110 %
1(
#143
0(
#144
b000111 %
1(
#145
0(
#146
b001000 %
1(
#147
0(
#148
b001001 %
1(
#149
0(
#150
b001010 %
1(
#151
0(
#152
b001011 %
1(
#153
0(
#154
b001100 %
1(
#155
0(
#156
b001101 %
1(
#157
0(
#158
b001110 %
1(
#159
0(
#160
b001111 %
1(
#161
0(
#162
b010000 %
1(
#163
0(
#164
b010001 %
1(
#165
0(
#166
b010010 %
1(
#167
0(
#168
b010011 %
1(
#169
0(
#170
b000000 %
1(
#171
0(
#172
b000001 %
1(
#173
0(
#174
b000010 %
1&
1(
#175
0(
#176
b000011 %
0&
b0101 '
1(
0,
#177
0(
#178
b000100 %
1(
#179
0(
#180
b000101 %
1(
#181
0(
#182
b000110 %
1(
#183
0(
#184
b000111 %
1(
#185
0(
#186
b001000 %
1(
#187
0(
#188
b001001 %
1(
#189
0(
#190
b001010 %
1(
#191
0(
#192
b001011 %
1(
#193
0(
#194
b001100 %
1(
#195
0(
#196
b001101 %
1(
#197
0(
#198
b001110 %
1(
#199
0(
#200
b001111 %
1(
#201
0(
#202
b010000 %
1(
#203
0(
#204
b010001 %
1(
#205
0(
#206
b010010 %
1(
#207
0(
#208
b010011 %
1(
#209
0(
#210
b000000 %
1(
#211
0(
#212
b000001 %
1(
#213
0(
#214
b000010 %
1&
1(
#215
0(
#216
b000011 %
0&
b0110 '
1(
#217
0(
#218
b000100 %
1(
#219
0(
#220
b000101 %
1(
#221
0(
#222
b000110 %
1(
#223
0(
#224
b000111 %
1(
#225
0(
#226
b001000 %
1(
#227
0(
#228
b001001 %
1(
#229
0(
#230
b001010 %
1(
#231
0(
#232
b001011 %
1(
#233
0(
#234
b001100 %
1(
#235
0(
#236
b001101 %
1(
#237
0(
#238
b001110 %
1(
#239
0(
#240
b001111 %
1(
#241
0(
#242
b010000 %
1(
#243
0(
#244
b010001 %
1(
#245
0(
#246
b010010 %
1(
#247
0(
#248
b010011 %
1(
#249
0(
#250
b000000 %
1(
#251
0(
#252
b000001 %
1(
#253
0(
#254
b000010 %
1&
1(
#255
0(
#256
b000011 %
0&
b0111 '
1(
1,
#257
0(
#258
b000100 %
1(
#259
0(
#260
b000101 %
1(
#261
0(
#262
b000110 %
1(
#263
0(
#264
b000111 %
1(
#265
0(
#266
b001000 %
1(
#267
0(
#268
b001001 %
1(
#269
0(
#270
b001010 %
1(
#271
0(
#272
b001011 %
1(
#273
0(
#274
b001100 %
1(
#275
0(
#276
b001101 %
1(
#277
0(
#278
b001110 %
1(
#279
0(
#280
b001111 %
1(
#281
0(
#282
b010000 %
1(
#283
0(
#284
b010001 %
1(
#285
0(
#286
b010010 %
1(
#287
0(
#288
b010011 %
1(
#289
0(
#290
b000000 %
1(
#291
0(
#292
b000001 %
1(
#293
0(
#294
b000010 %
1&
1(
#295
0(
#296
b000011 %
0&
b1000 '
1(
#297
0(
#298
b000100 %
1(
#299
0(
#300
b000101 %
1(
#301
0(
#302
b000110 %
1(
#303
0(
#304
b000111 %
1(
#305
0(
#306
b001000 %
1(
#307
0(
#308
b001001 %
1(
#309
0(
#310
b001010 %
1(
#311
0(
#312
b001011 %
1(
#313
0(
#314
b001100 %
1(
#315
0(
#316
b001101 %
1(
#317
0(
#318
b001110 %
1(
#319
0(
#320
b001111 %
1(
#321
0(
#322
b010000 %
1(
#323
0(
#324
b010001 %
1(
#325
0(
#326
b010010 %
1(
#327
0(
#328
b010011 %
1(
#329
0(
#330
b000000 %
1(
#331
0(
#332
b000001 %
1(
#333
0(
#334
b000010 %
1&
1(
#335
0(
#336
b000011 %
0&
b1001 '
1(
#337
0(
#338
b000100 %
1(
#339
0(
#340
b000101 %
1(
#341
0(
#342
b000110 %
1(
#343
0(
#344
b000111 %
1(
#345
0(
#346
b001000 %
1(
#347
0(
#348
b001001 %
1(
#349
0(
#350
b001010 %
1(
#351
0(
#352
b001011 %
1(
#353
0(
#354
b001100 %
1(
#355
0(
#356
b001101 %
1(
#357
0(
#358
b001110 %
1(
#359
0(
#360
b001111 %
1(
#361
0(
#362
b010000 %
1(
#363
0(
#364
b010001 %
1(
#365
0(
#366
b010010 %
1(
#367
0(
#368
b010011 %
1(
#369
0(
#370
b000000 %
1(
#371
0(
#372
b000001 %
1(
#373
0(
#374
b000010 %
1&
1(
#375
0(
#376
0$
b000011 %
0&
b0000 '
1(
#377
0(
#378
b000000 %
1(
