pulse_count/pulse_count.v
module pulse_count(
    input               clk,
    input               rst_n,
    input               pulse,
    output  reg [3:0]   count
);

reg     toggle;
always @(posedge pulse or negedge rst_n) begin
    if(!rst_n)
        toggle <= 1'b0;
    else
        toggle <= ~toggle;
end

reg     toggle_d1;
reg     toggle_d2;
always @(posedge clk or negedge rst_n) begin
    if(!rst_n) begin
        toggle_d1 <= 1'b0;
        toggle_d2 <= 1'b0;
    end else begin
        toggle_d1 <= toggle;
        toggle_d2 <= toggle_d1;
    end
end

wire    pulse_sync;
assign pulse_sync = toggle_d1 ^ toggle_d2;

always @(posedge clk or negedge rst_n) begin
    if(!rst_n)
        count <= 'd0;
    else if(pulse_sync)
        count <= count + 1'b1;
    else
        count <= count;
end

endmodule

pulse_count/waveform.vcd
$version Generated by VerilatedVcd $end
$timescale 1ps $end

 $scope module TOP $end
  $var wire  1 & clk $end
  $var wire  4 ) count [3:0] $end
  $var wire  1 ( pulse $end
  $var wire  1 ' rst_n $end
  $scope module pulse_count $end
   $var wire  1 & clk $end
   $var wire  4 ) count [3:0] $end
   $var wire  1 ( pulse $end
   $var wire  1 % pulse_sync $end
   $var wire  1 ' rst_n $end
   $var wire  1 * toggle $end
   $var wire  1 # toggle_d1 $end
   $var wire  1 $ toggle_d2 $end
  $upscope $end
 $upscope $end
$enddefinitions $end


#0
0#
0$
0%
1&
1'
0(
b0000 )
0*
#1
0&
0'
#2
1&
#3
0&
#4
1&
#5
0&
#6
1&
1'
#7
0&
#8
1&
#9
0&
#10
1&
1(
#11
0&
0(
1*
#12
1#
1%
1&
#13
0&
#14
1$
0%
1&
b0001 )
#15
0&
#16
1&
#17
0&
#18
1&
#19
0&
#20
1&
1(
#21
0&
0(
0*
#22
0#
1%
1&
#23
0&
#24
0$
0%
1&
b0010 )
#25
0&
#26
1&
1(
#27
0&
0(
1*
#28
1#
1%
1&
#29
0&
#30
1$
0%
1&
1(
b0011 )
#31
0&
0(
0*
#32
0#
1%
1&
#33
0&
#34
0$
0%
1&
b0100 )
