traffic_light/triffic_light.v
`timescale 1ns/1ns

module triffic_light #(parameter
    RED_CNT     =   10,
    YELLOW_CNT  =   5,
    GREEN_CNT   =   60
)(
    input rst_n, //异位复位信号，低电平有效
    input clk, //时钟信号
    input pass_request,
    output wire[7:0]clock,
    output reg red,
    output reg yellow,
    output reg green
);

localparam  RED     =   3'b001,
            YELLOW  =   3'b010,
            GREEN   =   3'b100;

reg [2:0]   cstate;
reg [2:0]   nstate;

always @(posedge clk or negedge rst_n) begin
    if (!rst_n)
        cstate <= RED;
    else
        cstate <= nstate;
end

always @(*) begin

    case(cstate)
    RED:
        if(cnt_red == 1)
            nstate = YELLOW;
        else
            nstate = RED;
    YELLOW:
        if(cnt_yellow == 1)
            nstate = GREEN;
        else
            nstate = YELLOW;
    GREEN:
        if(cnt_green == 1)
            nstate = RED;
        else
            nstate = GREEN;
    default: nstate = nstate;
    endcase
end

reg [3:0] cnt_red;
always @(posedge clk or negedge rst_n) begin
    if(!rst_n)
        cnt_red <= RED_CNT;
    else if(cstate == RED)
        cnt_red <= cnt_red - 1'b1;
    else
        cnt_red <= 'd0;
end

reg [2:0] cnt_yellow;
always @(posedge clk or negedge rst_n) begin
    if(!rst_n)
        cnt_yellow <= YELLOW_CNT;
    else if(cstate == YELLOW)
        cnt_yellow <= cnt_yellow - 1'b1;
    else
        cnt_yellow <= 'd0;
end

reg [5:0] cnt_green;
always @(posedge clk or negedge rst_n) begin
    if(!rst_n)
        cnt_green <= GREEN_CNT;
    else if(cstate == GREEN && pass_request && cnt_green > 10)
        cnt_green <= 10;
    else if(cstate == GREEN)
        cnt_green <= cnt_green - 1'b1;
    else
        cnt_green <= 'd0;
end

always @(posedge clk or negedge rst_n) begin
    if(!rst_n)
        red <= 1'b0;
    else if(cstate == RED)
        red <= 1'b1;
    else
        red <= 1'b0;
end

always @(posedge clk or negedge rst_n) begin
    if(!rst_n)
        yellow <= 1'b0;
    else if(cstate == YELLOW)
        yellow <= 1'b1;
    else
        yellow <= 1'b0;
end

always @(posedge clk or negedge rst_n) begin
    if(!rst_n)
        green <= 1'b0;
    else if(cstate == GREEN)
        green <= 1'b1;
    else
        green <= 1'b0;
end

assign clock =  (cstate == RED) ? {4'd0, cnt_red} : 
                (cstate == YELLOW) ? {5'd0, cnt_yellow} :
                (cstate == GREEN) ? {2'd0, cnt_green} :
                'd0;

endmodule

traffic_light/waveform.vcd
$version Generated by VerilatedVcd $end
$timescale 1ns $end

 $scope module TOP $end
  $var wire  1 ) clk $end
  $var wire  8 + clock [7:0] $end
  $var wire  1 . green $end
  $var wire  1 * pass_request $end
  $var wire  1 , red $end
  $var wire  1 ( rst_n $end
  $var wire  1 - yellow $end
  $scope module triffic_light $end
   $var wire  3 4 GREEN [2:0] $end
   $var wire 32 1 GREEN_CNT [31:0] $end
   $var wire  3 2 RED [2:0] $end
   $var wire 32 / RED_CNT [31:0] $end
   $var wire  3 3 YELLOW [2:0] $end
   $var wire 32 0 YELLOW_CNT [31:0] $end
   $var wire  1 ) clk $end
   $var wire  8 + clock [7:0] $end
   $var wire  6 ' cnt_green [5:0] $end
   $var wire  4 % cnt_red [3:0] $end
   $var wire  3 & cnt_yellow [2:0] $end
   $var wire  3 # cstate [2:0] $end
   $var wire  1 . green $end
   $var wire  3 $ nstate [2:0] $end
   $var wire  1 * pass_request $end
   $var wire  1 , red $end
   $var wire  1 ( rst_n $end
   $var wire  1 - yellow $end
  $upscope $end
 $upscope $end
$enddefinitions $end


#0
b000 #
b000 $
b0000 %
b000 &
b000000 '
1(
1)
0*
b00000000 +
0,
0-
0.
b00000000000000000000000000001010 /
b00000000000000000000000000000101 0
b00000000000000000000000000111100 1
b001 2
b010 3
b100 4
#1
0)
#2
b001 #
b001 $
b1010 %
b101 &
b111100 '
0(
1)
b00001010 +
#3
0)
#4
1)
#5
0)
#6
b1001 %
b000 &
b000000 '
1(
1)
b00001001 +
1,
#7
0)
#8
b1000 %
1)
b00001000 +
#9
0)
#10
b0111 %
1)
b00000111 +
#11
0)
#12
b0110 %
1)
b00000110 +
#13
0)
#14
b0101 %
1)
b00000101 +
#15
0)
#16
b0100 %
1)
b00000100 +
#17
0)
#18
b0011 %
1)
b00000011 +
#19
0)
#20
b0010 %
1)
b00000010 +
#21
0)
#22
b010 $
b0001 %
1)
b00000001 +
#23
0)
#24
b010 #
b0000 %
1)
b00000000 +
#25
0)
#26
b111 &
1)
b00000111 +
0,
1-
#27
0)
#28
b110 &
1)
b00000110 +
#29
0)
#30
b101 &
1)
b00000101 +
#31
0)
#32
b100 &
1)
b00000100 +
#33
0)
#34
b011 &
1)
b00000011 +
#35
0)
#36
b010 &
1)
b00000010 +
#37
0)
#38
b100 $
b001 &
1)
b00000001 +
#39
0)
#40
b100 #
b000 &
1)
b00000000 +
#41
0)
#42
b111111 '
1)
b00111111 +
0-
1.
#43
0)
#44
b111110 '
1)
b00111110 +
#45
0)
#46
b111101 '
1)
b00111101 +
#47
0)
#48
b111100 '
1)
b00111100 +
#49
0)
#50
b111011 '
1)
b00111011 +
#51
0)
#52
b111010 '
1)
b00111010 +
#53
0)
#54
b111001 '
1)
b00111001 +
#55
0)
#56
b111000 '
1)
b00111000 +
#57
0)
#58
b110111 '
1)
b00110111 +
#59
0)
#60
b110110 '
1)
b00110110 +
#61
0)
#62
b110101 '
1)
b00110101 +
#63
0)
#64
b110100 '
1)
b00110100 +
#65
0)
#66
b110011 '
1)
b00110011 +
#67
0)
#68
b110010 '
1)
b00110010 +
#69
0)
#70
b110001 '
1)
b00110001 +
#71
0)
#72
b110000 '
1)
b00110000 +
#73
0)
#74
b101111 '
1)
b00101111 +
#75
0)
#76
b101110 '
1)
b00101110 +
#77
0)
#78
b101101 '
1)
b00101101 +
#79
0)
#80
b101100 '
1)
b00101100 +
#81
0)
#82
b101011 '
1)
b00101011 +
#83
0)
#84
b101010 '
1)
b00101010 +
#85
0)
#86
b101001 '
1)
b00101001 +
#87
0)
#88
b101000 '
1)
b00101000 +
#89
0)
#90
b100111 '
1)
b00100111 +
#91
0)
#92
b100110 '
1)
b00100110 +
#93
0)
#94
b100101 '
1)
b00100101 +
#95
0)
#96
b100100 '
1)
b00100100 +
#97
0)
#98
b100011 '
1)
b00100011 +
#99
0)
#100
b100010 '
1)
b00100010 +
#101
0)
#102
b100001 '
1)
b00100001 +
#103
0)
#104
b100000 '
1)
b00100000 +
#105
0)
#106
b011111 '
1)
b00011111 +
#107
0)
#108
b011110 '
1)
b00011110 +
#109
0)
#110
b011101 '
1)
b00011101 +
#111
0)
#112
b011100 '
1)
b00011100 +
#113
0)
#114
b011011 '
1)
b00011011 +
#115
0)
#116
b011010 '
1)
b00011010 +
#117
0)
#118
b011001 '
1)
b00011001 +
#119
0)
#120
b011000 '
1)
b00011000 +
#121
0)
#122
b010111 '
1)
b00010111 +
#123
0)
#124
b010110 '
1)
b00010110 +
#125
0)
#126
b010101 '
1)
b00010101 +
#127
0)
#128
b010100 '
1)
b00010100 +
#129
0)
#130
b010011 '
1)
b00010011 +
#131
0)
#132
b010010 '
1)
b00010010 +
#133
0)
#134
b010001 '
1)
b00010001 +
#135
0)
#136
b010000 '
1)
b00010000 +
#137
0)
#138
b001111 '
1)
b00001111 +
#139
0)
#140
b001110 '
1)
b00001110 +
#141
0)
#142
b001101 '
1)
b00001101 +
#143
0)
#144
b001100 '
1)
b00001100 +
#145
0)
#146
b001011 '
1)
b00001011 +
#147
0)
#148
b001010 '
1)
b00001010 +
#149
0)
#150
b001001 '
1)
b00001001 +
#151
0)
#152
b001000 '
1)
b00001000 +
#153
0)
#154
b000111 '
1)
b00000111 +
#155
0)
#156
b000110 '
1)
b00000110 +
#157
0)
#158
b000101 '
1)
b00000101 +
#159
0)
#160
b000100 '
1)
b00000100 +
#161
0)
#162
b000011 '
1)
b00000011 +
#163
0)
#164
b000010 '
1)
b00000010 +
#165
0)
#166
b001 $
b000001 '
1)
b00000001 +
#167
0)
#168
b001 #
b000000 '
1)
b00000000 +
#169
0)
#170
b1111 %
1)
b00001111 +
1,
0.
#171
0)
#172
b1110 %
1)
b00001110 +
#173
0)
#174
b1101 %
1)
b00001101 +
#175
0)
#176
b1100 %
1)
b00001100 +
#177
0)
#178
b1011 %
1)
b00001011 +
#179
0)
#180
b1010 %
1)
b00001010 +
#181
0)
#182
b1001 %
1)
b00001001 +
#183
0)
#184
b1000 %
1)
b00001000 +
#185
0)
#186
b0111 %
1)
b00000111 +
#187
0)
#188
b0110 %
1)
b00000110 +
#189
0)
#190
b0101 %
1)
b00000101 +
#191
0)
#192
b0100 %
1)
b00000100 +
#193
0)
#194
b0011 %
1)
b00000011 +
#195
0)
#196
b0010 %
1)
b00000010 +
#197
0)
#198
b010 $
b0001 %
1)
b00000001 +
#199
0)
#200
b010 #
b0000 %
1)
b00000000 +
#201
0)
#202
b111 &
1)
b00000111 +
0,
1-
#203
0)
#204
b110 &
1)
b00000110 +
#205
0)
#206
b101 &
1)
b00000101 +
#207
0)
#208
b100 &
1)
b00000100 +
#209
0)
#210
b011 &
1)
b00000011 +
#211
0)
#212
b010 &
1)
b00000010 +
#213
0)
#214
b100 $
b001 &
1)
b00000001 +
#215
0)
#216
b100 #
b000 &
1)
b00000000 +
#217
0)
#218
b111111 '
1)
b00111111 +
0-
1.
#219
0)
#220
b111110 '
1)
b00111110 +
#221
0)
#222
b111101 '
1)
b00111101 +
#223
0)
#224
b111100 '
1)
b00111100 +
#225
0)
#226
b111011 '
1)
b00111011 +
#227
0)
#228
b111010 '
1)
b00111010 +
#229
0)
#230
b111001 '
1)
b00111001 +
#231
0)
#232
b111000 '
1)
b00111000 +
#233
0)
#234
b110111 '
1)
b00110111 +
#235
0)
#236
b110110 '
1)
b00110110 +
#237
0)
#238
b110101 '
1)
b00110101 +
#239
0)
#240
b110100 '
1)
b00110100 +
#241
0)
#242
b110011 '
1)
b00110011 +
#243
0)
#244
b110010 '
1)
b00110010 +
#245
0)
#246
b110001 '
1)
b00110001 +
#247
0)
#248
b110000 '
1)
b00110000 +
#249
0)
#250
b101111 '
1)
b00101111 +
#251
0)
#252
b101110 '
1)
b00101110 +
#253
0)
#254
b101101 '
1)
b00101101 +
#255
0)
#256
b101100 '
1)
b00101100 +
#257
0)
#258
b101011 '
1)
b00101011 +
#259
0)
#260
b101010 '
1)
b00101010 +
#261
0)
#262
b101001 '
1)
b00101001 +
#263
0)
#264
b101000 '
1)
b00101000 +
#265
0)
#266
b100111 '
1)
b00100111 +
#267
0)
#268
b100110 '
1)
b00100110 +
#269
0)
#270
b100101 '
1)
b00100101 +
#271
0)
#272
b100100 '
1)
b00100100 +
#273
0)
#274
b100011 '
1)
b00100011 +
#275
0)
#276
b100010 '
1)
b00100010 +
#277
0)
#278
b100001 '
1)
b00100001 +
#279
0)
#280
b100000 '
1)
b00100000 +
#281
0)
#282
b011111 '
1)
b00011111 +
#283
0)
#284
b011110 '
1)
b00011110 +
#285
0)
#286
b011101 '
1)
b00011101 +
#287
0)
#288
b011100 '
1)
b00011100 +
#289
0)
#290
b011011 '
1)
b00011011 +
#291
0)
#292
b011010 '
1)
b00011010 +
#293
0)
#294
b011001 '
1)
b00011001 +
#295
0)
#296
b011000 '
1)
b00011000 +
#297
0)
#298
b010111 '
1)
b00010111 +
